// converted by version  [v3.0.2]
// on Fri Nov 08 11:48:59 CET 2013

.package uicc/hci/test/framework/api_1_hsr_ace {
	.aid 0xA0:0x0:0x0:0x0:0x9:0x0:0x5:0xFF:0xFF:0xFF:0xFF:0x89:0x21:0x0:0x0:0x0;
	.version 1.0;

	.imports {
		0xA0:0x0:0x0:0x0:0x62:0x1:0x1 1.4;		//javacard/framework
		0xA0:0x0:0x0:0x0:0x9:0x0:0x5:0xFF:0xFF:0xFF:0xFF:0x89:0x16:0x1:0x0:0x0 1.0;		//uicc/hci/framework
		0xA0:0x0:0x0:0x0:0x9:0x0:0x5:0xFF:0xFF:0xFF:0xFF:0x89:0x16:0x2:0x1:0x0 1.0;		//uicc/hci/services/cardemulation
		0xA0:0x0:0x0:0x0:0x62:0x0:0x1 1.0;		//java/lang
		0xA0:0x0:0x0:0x0:0x9:0x0:0x5:0xFF:0xFF:0xFF:0xFF:0x89:0x16:0x2:0x2:0x0 1.0;		//uicc/hci/services/connectivity
		0xA0:0x0:0x0:0x0:0x9:0x0:0x5:0xFF:0xFF:0xFF:0xFF:0x89:0x16:0x2:0x3:0x0 1.0;		//uicc/hci/services/readermode
		0xA0:0x0:0x0:0x1:0x51:0x2 1.0;		//org/globalplatform/contactless
	}

	.applet {
		0xA0:0x0:0x0:0x0:0x9:0x0:0x5:0xFF:0xFF:0xFF:0xFF:0x89:0x21:0x6:0x1:0x2 Api_1_Hsr_Ace_1;
		0xA0:0x0:0x0:0x0:0x9:0x0:0x5:0xFF:0xFF:0xFF:0xFF:0x89:0x21:0x6:0x2:0x2 Api_1_Hsr_Ace_2;
		0xA0:0x0:0x0:0x0:0x9:0x0:0x5:0xFF:0xFF:0xFF:0xFF:0x89:0x21:0x6:0x3:0x2 Api_1_Hsr_Ace_3;
		0xA0:0x0:0x0:0x0:0x9:0x0:0x5:0xFF:0xFF:0xFF:0xFF:0x89:0x21:0x6:0x4:0x2 Api_1_Hsr_Ace_4;
		0xA0:0x0:0x0:0x0:0x9:0x0:0x5:0xFF:0xFF:0xFF:0xFF:0x89:0x21:0x6:0x5:0x2 Api_1_Hsr_Ace_5;
		0xA0:0x0:0x0:0x0:0x9:0x0:0x5:0xFF:0xFF:0xFF:0xFF:0x89:0x21:0x6:0x6:0x2 Api_1_Hsr_Ace_6;
		0xA0:0x0:0x0:0x0:0x9:0x0:0x5:0xFF:0xFF:0xFF:0xFF:0x89:0x21:0x6:0x7:0x2 Api_1_Hsr_Ace_7;
		0xA0:0x0:0x0:0x0:0x9:0x0:0x5:0xFF:0xFF:0xFF:0xFF:0x89:0x21:0x6:0x8:0x2 Api_1_Hsr_Ace_8;
		0xA0:0x0:0x0:0x0:0x9:0x0:0x5:0xFF:0xFF:0xFF:0xFF:0x89:0x21:0x6:0x9:0x2 Api_1_Hsr_Ace_9;
	}

	.constantPool {
		// 0
		instanceFieldRef 2.2 Api_1_Hsr_Ace_1/ceService;
		// 1
		instanceFieldRef 4.2 Api_1_Hsr_Ace_2/cnnService;
		// 2
		instanceFieldRef 5.2 Api_1_Hsr_Ace_3/rdrService;
		// 3
		instanceFieldRef 2.2 Api_1_Hsr_Ace_4/ceService;
		// 4
		instanceFieldRef byte[] Api_1_Hsr_Ace_5/ibuffer;
		// 5
		instanceFieldRef byte[] Api_1_Hsr_Ace_5/verificationByte;
		// 6
		instanceFieldRef 2.2 Api_1_Hsr_Ace_5/ceService;
		// 7
		instanceFieldRef byte[] Api_1_Hsr_Ace_6/verificationByte;
		// 8
		instanceFieldRef byte[] Api_1_Hsr_Ace_6/ibuffer;
		// 9
		instanceFieldRef 2.2 Api_1_Hsr_Ace_6/ceService;
		// 10
		instanceFieldRef 5.2 Api_1_Hsr_Ace_7/rdrService;
		// 11
		instanceFieldRef byte Api_1_Hsr_Ace_8/verificationByte;
		// 12
		instanceFieldRef 2.2 Api_1_Hsr_Ace_8/ceService;
		// 13
		instanceFieldRef 5.2 Api_1_Hsr_Ace_9/rdrService;
		// 14
		.classRef 4.2;		// uicc/hci/services/connectivity/ConnectivityService
		// 15
		.classRef 1.3;		// uicc/hci/framework/HCIException
		// 16
		.classRef Api_1_Hsr_Ace_2;
		// 17
		staticMethodRef Api_1_Hsr_Ace_2/<init>()V;
		// 18
		virtualMethodRef 0.3.3()Z;		// selectingApplet()Z
		// 19
		virtualMethodRef 0.3.1()V;		// register()V
		// 20
		.classRef 5.2;		// uicc/hci/services/readermode/ReaderService
		// 21
		virtualMethodRef 0.3.1()V;		// register()V
		// 22
		.classRef Api_1_Hsr_Ace_3;
		// 23
		staticMethodRef Api_1_Hsr_Ace_3/<init>()V;
		// 24
		virtualMethodRef 0.3.3()Z;		// selectingApplet()Z
		// 25
		virtualMethodRef 0.3.1()V;		// register()V
		// 26
		staticMethodRef 1.4.0(S)Luicc/hci/framework/HCIService;;		// uicc/hci/framework/HCIDevice.getHCIService(S)Luicc/hci/framework/HCIService;
			.descriptor	Luicc/hci/framework/HCIService;	1.2;

		// 27
		.classRef Api_1_Hsr_Ace_4;
		// 28
		staticMethodRef Api_1_Hsr_Ace_4/<init>()V;
		// 29
		virtualMethodRef 0.3.3()Z;		// selectingApplet()Z
		// 30
		virtualMethodRef 0.3.1()V;		// register()V
		// 31
		staticMethodRef 0.8.13(SB)[B;		// javacard/framework/JCSystem.makeTransientByteArray(SB)[B
		// 32
		.classRef 2.2;		// uicc/hci/services/cardemulation/CardEmulationService
		// 33
		staticMethodRef 0.3.0()V;		// javacard/framework/Applet.<init>()V
		// 34
		staticMethodRef 0.7.1(S)V;		// javacard/framework/ISOException.throwIt(S)V
		// 35
		.classRef Api_1_Hsr_Ace_5;
		// 36
		staticMethodRef Api_1_Hsr_Ace_5/<init>()V;
		// 37
		virtualMethodRef 0.3.3()Z;		// selectingApplet()Z
		// 38
		superMethodRef Api_1_Hsr_Ace_5/deselect()V;
		// 39
		.classRef 2.1;		// uicc/hci/services/cardemulation/CardEmulationMessage
		// 40
		virtualMethodRef 0.3.1()V;		// register()V
		// 41
		.classRef Api_1_Hsr_Ace_1;
		// 42
		staticMethodRef Api_1_Hsr_Ace_1/<init>()V;
		// 43
		virtualMethodRef 0.3.3()Z;		// selectingApplet()Z
		// 44
		.classRef Api_1_Hsr_Ace_6;
		// 45
		staticMethodRef Api_1_Hsr_Ace_6/<init>()V;
		// 46
		virtualMethodRef 0.3.3()Z;		// selectingApplet()Z
		// 47
		virtualMethodRef 0.3.1()V;		// register()V
		// 48
		virtualMethodRef 0.10.1()[B;		// getBuffer()[B
		// 49
		.classRef Api_1_Hsr_Ace_7;
		// 50
		staticMethodRef Api_1_Hsr_Ace_7/<init>()V;
		// 51
		virtualMethodRef 0.3.3()Z;		// selectingApplet()Z
		// 52
		virtualMethodRef 0.3.1()V;		// register()V
		// 53
		virtualMethodRef 1.3.1()S;		// getReason()S
		// 54
		virtualMethodRef 0.10.8(SS)V;		// setOutgoingAndSend(SS)V
		// 55
		.classRef Api_1_Hsr_Ace_8;
		// 56
		staticMethodRef Api_1_Hsr_Ace_8/<init>()V;
		// 57
		virtualMethodRef 0.3.3()Z;		// selectingApplet()Z
		// 58
		superMethodRef Api_1_Hsr_Ace_8/select()Z;
		// 59
		virtualMethodRef 0.3.1()V;		// register()V
		// 60
		virtualMethodRef 0.3.1()V;		// register()V
		// 61
		.classRef Api_1_Hsr_Ace_9;
		// 62
		staticMethodRef Api_1_Hsr_Ace_9/<init>()V;
		// 63
		virtualMethodRef 0.3.3()Z;		// selectingApplet()Z
		// 64
		staticMethodRef 6.5.4(SZ)V;		// org/globalplatform/contactless/GPCLSystem.setCommunicationInterface(SZ)V
	}

	.class public Api_1_Hsr_Ace_1 0 extends 0.3 {		// extends javacard/framework/Applet

		.shareable;

		.fields {
			private 2.2 ceService 0;		// Luicc/hci/services/cardemulation/CardEmulationService;
			private static final short SW_EVENT_NOT_SUPPORTED = 28417;		// S
			private static final short SW_METHOD_NOT_SUPPORTED = 28418;		// S
			private static final byte INS_EVENT_TM_FAILED = 16;		// B
			private static final byte INS_EVENT_RCP_FAILED = 17;		// B
			private static final byte INS_EVENT_GET_PARAM = 18;		// B
			private static final byte INS_EVENT_FIELD_OFF = 19;		// B
			private static final byte INS_EVENT_SEND_DATA = 20;		// B
			private static final byte INS_EVENT_WRONG_CONDITION = 21;		// B
			private static final byte INS_WRONG_EVENT = 22;		// B
		}

		.publicMethodTable 7 {
			equals(Ljava/lang/Object;)Z;
			register()V;
			register([BSB)V;
			selectingApplet()Z;
			deselect()V;
			getShareableInterfaceObject(Ljavacard/framework/AID;B)Ljavacard/framework/Shareable;;
			select()Z;
			process(Ljavacard/framework/APDU;)V;
			onCallback(BLuicc/hci/framework/HCIMessage;)V;
		}

		.packageMethodTable 0 {
		}

		.implementedInterfaceInfoTable { 
			.interface 0.2 { 		// javacard/framework/Shareable
			}

			.interface 1.0 { 		// uicc/hci/framework/HCIListener
				8;		// onCallback(BLuicc/hci/framework/HCIMessage;)V
			}

			.interface 2.0 { 		// uicc/hci/services/cardemulation/CardEmulationListener
				8;		// onCallback(BLuicc/hci/framework/HCIMessage;)V
			}

		}

		.method private <init>()V {
			.stack 2;
			.locals 1;

				L0:	aload_0;
					invokespecial 33;		// javacard/framework/Applet.<init>()V
					aload_0;
					invokevirtual 21;		// register()V
				L1:	aload_0;
					sconst_3;
					invokestatic 26;		// uicc/hci/framework/HCIDevice.getHCIService(S)Luicc/hci/framework/HCIService;
					checkcast 0 32;		// T_CLASSORINTERFACE uicc/hci/services/cardemulation/CardEmulationService
					putfield_a 0;		// reference uicc/hci/test/framework/api_1_hsr_ace/Api_1_Hsr_Ace_1.ceService
					getfield_a_this 0;		// reference uicc/hci/test/framework/api_1_hsr_ace/Api_1_Hsr_Ace_1.ceService
					aload_0;
					invokeinterface 2 32 0;		// uicc/hci/services/cardemulation/CardEmulationService
				L2:	goto L4;
				L3:	astore_1;
					sspush 27012;
					invokestatic 34;		// javacard/framework/ISOException.throwIt(S)V
				L4:	return;
			.exceptionTable {
				// start_block end_block handler_block catch_type_index
				L1 L2 L3 15;
			}
		}

		.method public static install([BSB)V 0 {
			.stack 2;
			.locals 0;

				L0:	new 41;		// uicc/hci/test/framework/api_1_hsr_ace/Api_1_Hsr_Ace_1
					dup;
					invokespecial 42;		// uicc/hci/test/framework/api_1_hsr_ace/Api_1_Hsr_Ace_1.<init>()V
					pop;
					return;
		}

		.method public process(Ljavacard/framework/APDU;)V 7 {
			.stack 3;
			.locals 2;

			.descriptor	Ljavacard/framework/APDU;	0.10;

				L0:	aload_0;
					invokevirtual 43;		// selectingApplet()Z
					ifeq L2;
				L1:	return;
				L2:	aload_1;
					invokevirtual 48;		// getBuffer()[B
					astore_2;
					aload_2;
					sconst_1;
					baload;
					stableswitch L35 16 22 L3 L7 L11 L19 L15 L23 L29;
				L3:	getfield_a_this 0;		// reference uicc/hci/test/framework/api_1_hsr_ace/Api_1_Hsr_Ace_1.ceService
					bspush -127;
					invokeinterface 2 32 3;		// uicc/hci/services/cardemulation/CardEmulationService
				L4:	goto L6;
				L5:	astore_3;
					sspush 28418;
					invokestatic 34;		// javacard/framework/ISOException.throwIt(S)V
				L6:	return;
				L7:	getfield_a_this 0;		// reference uicc/hci/test/framework/api_1_hsr_ace/Api_1_Hsr_Ace_1.ceService
					bspush -126;
					invokeinterface 2 32 3;		// uicc/hci/services/cardemulation/CardEmulationService
				L8:	goto L10;
				L9:	astore_3;
					sspush 28418;
					invokestatic 34;		// javacard/framework/ISOException.throwIt(S)V
				L10:	return;
				L11:	getfield_a_this 0;		// reference uicc/hci/test/framework/api_1_hsr_ace/Api_1_Hsr_Ace_1.ceService
					sconst_1;
					invokeinterface 2 32 3;		// uicc/hci/services/cardemulation/CardEmulationService
				L12:	goto L14;
				L13:	astore_3;
					sspush 28418;
					invokestatic 34;		// javacard/framework/ISOException.throwIt(S)V
				L14:	return;
				L15:	getfield_a_this 0;		// reference uicc/hci/test/framework/api_1_hsr_ace/Api_1_Hsr_Ace_1.ceService
					bspush 80;
					invokeinterface 2 32 3;		// uicc/hci/services/cardemulation/CardEmulationService
				L16:	goto L18;
				L17:	astore_3;
					sspush 28418;
					invokestatic 34;		// javacard/framework/ISOException.throwIt(S)V
				L18:	return;
				L19:	getfield_a_this 0;		// reference uicc/hci/test/framework/api_1_hsr_ace/Api_1_Hsr_Ace_1.ceService
					bspush 84;
					invokeinterface 2 32 3;		// uicc/hci/services/cardemulation/CardEmulationService
				L20:	goto L22;
				L21:	astore_3;
					sspush 28418;
					invokestatic 34;		// javacard/framework/ISOException.throwIt(S)V
				L22:	return;
				L23:	getfield_a_this 0;		// reference uicc/hci/test/framework/api_1_hsr_ace/Api_1_Hsr_Ace_1.ceService
					sconst_1;
					invokeinterface 2 32 3;		// uicc/hci/services/cardemulation/CardEmulationService
				L24:	goto L28;
				L25:	astore_3;
					aload_3;
					invokevirtual 53;		// getReason()S
					bspush 10;
					if_scmpne L27;
				L26:	return;
				L27:	sspush 28418;
					invokestatic 34;		// javacard/framework/ISOException.throwIt(S)V
				L28:	sspush 28417;
					invokestatic 34;		// javacard/framework/ISOException.throwIt(S)V
				L29:	getfield_a_this 0;		// reference uicc/hci/test/framework/api_1_hsr_ace/Api_1_Hsr_Ace_1.ceService
					sconst_2;
					invokeinterface 2 32 3;		// uicc/hci/services/cardemulation/CardEmulationService
				L30:	goto L34;
				L31:	astore_3;
					aload_3;
					invokevirtual 53;		// getReason()S
					bspush 6;
					if_scmpne L33;
				L32:	return;
				L33:	sspush 28418;
					invokestatic 34;		// javacard/framework/ISOException.throwIt(S)V
				L34:	sspush 28417;
					invokestatic 34;		// javacard/framework/ISOException.throwIt(S)V
					return;
				L35:	sspush 27904;
					invokestatic 34;		// javacard/framework/ISOException.throwIt(S)V
					aload_1;
					sconst_0;
					sconst_0;
					invokevirtual 54;		// setOutgoingAndSend(SS)V
					return;
			.exceptionTable {
				// start_block end_block handler_block catch_type_index
				L3 L4 L5 15;
				L7 L8 L9 15;
				L11 L12 L13 15;
				L15 L16 L17 15;
				L19 L20 L21 15;
				L23 L24 L25 15;
				L29 L30 L31 15;
			}
		}

		.method public onCallback(BLuicc/hci/framework/HCIMessage;)V 8 {
			.stack 0;
			.locals 0;

			.descriptor	Luicc/hci/framework/HCIMessage;	1.1;

				L0:	return;
		}

	}

	.class public Api_1_Hsr_Ace_2 1 extends 0.3 {		// extends javacard/framework/Applet

		.shareable;

		.fields {
			private 4.2 cnnService 0;		// Luicc/hci/services/connectivity/ConnectivityService;
			private static final short SW_EVENT_NOT_SUPPORTED = 28417;		// S
			private static final short SW_METHOD_NOT_SUPPORTED = 28418;		// S
			private static final byte INS_EVENT_TM_FAILED = 16;		// B
			private static final byte INS_EVENT_RCP_FAILED = 17;		// B
			private static final byte INS_EVENT_STAND_BY = 18;		// B
			private static final byte INS_WRONG_EVENT = 22;		// B
		}

		.publicMethodTable 7 {
			equals(Ljava/lang/Object;)Z;
			register()V;
			register([BSB)V;
			selectingApplet()Z;
			deselect()V;
			getShareableInterfaceObject(Ljavacard/framework/AID;B)Ljavacard/framework/Shareable;;
			select()Z;
			process(Ljavacard/framework/APDU;)V;
			onCallback(BLuicc/hci/framework/HCIMessage;)V;
		}

		.packageMethodTable 0 {
		}

		.implementedInterfaceInfoTable { 
			.interface 0.2 { 		// javacard/framework/Shareable
			}

			.interface 1.0 { 		// uicc/hci/framework/HCIListener
				8;		// onCallback(BLuicc/hci/framework/HCIMessage;)V
			}

			.interface 4.0 { 		// uicc/hci/services/connectivity/ConnectivityListener
				8;		// onCallback(BLuicc/hci/framework/HCIMessage;)V
			}

		}

		.method private <init>()V {
			.stack 2;
			.locals 1;

				L0:	aload_0;
					invokespecial 33;		// javacard/framework/Applet.<init>()V
					aload_0;
					invokevirtual 60;		// register()V
				L1:	aload_0;
					sconst_4;
					invokestatic 26;		// uicc/hci/framework/HCIDevice.getHCIService(S)Luicc/hci/framework/HCIService;
					checkcast 0 14;		// T_CLASSORINTERFACE uicc/hci/services/connectivity/ConnectivityService
					putfield_a 1;		// reference uicc/hci/test/framework/api_1_hsr_ace/Api_1_Hsr_Ace_2.cnnService
					getfield_a_this 1;		// reference uicc/hci/test/framework/api_1_hsr_ace/Api_1_Hsr_Ace_2.cnnService
					aload_0;
					invokeinterface 2 14 0;		// uicc/hci/services/connectivity/ConnectivityService
				L2:	goto L4;
				L3:	astore_1;
					sspush 27012;
					invokestatic 34;		// javacard/framework/ISOException.throwIt(S)V
				L4:	return;
			.exceptionTable {
				// start_block end_block handler_block catch_type_index
				L1 L2 L3 15;
			}
		}

		.method public static install([BSB)V 0 {
			.stack 2;
			.locals 0;

				L0:	new 16;		// uicc/hci/test/framework/api_1_hsr_ace/Api_1_Hsr_Ace_2
					dup;
					invokespecial 17;		// uicc/hci/test/framework/api_1_hsr_ace/Api_1_Hsr_Ace_2.<init>()V
					pop;
					return;
		}

		.method public process(Ljavacard/framework/APDU;)V 7 {
			.stack 2;
			.locals 2;

			.descriptor	Ljavacard/framework/APDU;	0.10;

				L0:	aload_0;
					invokevirtual 18;		// selectingApplet()Z
					ifeq L2;
				L1:	return;
				L2:	aload_1;
					invokevirtual 48;		// getBuffer()[B
					astore_2;
					aload_2;
					sconst_1;
					baload;
					stableswitch L21 16 22 L3 L7 L11 L21 L21 L21 L15;
				L3:	getfield_a_this 1;		// reference uicc/hci/test/framework/api_1_hsr_ace/Api_1_Hsr_Ace_2.cnnService
					bspush -127;
					invokeinterface 2 14 3;		// uicc/hci/services/connectivity/ConnectivityService
				L4:	goto L6;
				L5:	astore_3;
					sspush 28418;
					invokestatic 34;		// javacard/framework/ISOException.throwIt(S)V
				L6:	return;
				L7:	getfield_a_this 1;		// reference uicc/hci/test/framework/api_1_hsr_ace/Api_1_Hsr_Ace_2.cnnService
					bspush -126;
					invokeinterface 2 14 3;		// uicc/hci/services/connectivity/ConnectivityService
				L8:	goto L10;
				L9:	astore_3;
					sspush 28418;
					invokestatic 34;		// javacard/framework/ISOException.throwIt(S)V
				L10:	return;
				L11:	getfield_a_this 1;		// reference uicc/hci/test/framework/api_1_hsr_ace/Api_1_Hsr_Ace_2.cnnService
					bspush 80;
					invokeinterface 2 14 3;		// uicc/hci/services/connectivity/ConnectivityService
				L12:	goto L14;
				L13:	astore_3;
					sspush 28418;
					invokestatic 34;		// javacard/framework/ISOException.throwIt(S)V
				L14:	return;
				L15:	getfield_a_this 1;		// reference uicc/hci/test/framework/api_1_hsr_ace/Api_1_Hsr_Ace_2.cnnService
					sconst_2;
					invokeinterface 2 14 3;		// uicc/hci/services/connectivity/ConnectivityService
				L16:	goto L20;
				L17:	astore_3;
					aload_3;
					invokevirtual 53;		// getReason()S
					bspush 6;
					if_scmpne L19;
				L18:	return;
				L19:	sspush 28418;
					invokestatic 34;		// javacard/framework/ISOException.throwIt(S)V
				L20:	sspush 28417;
					invokestatic 34;		// javacard/framework/ISOException.throwIt(S)V
					return;
				L21:	sspush 27904;
					invokestatic 34;		// javacard/framework/ISOException.throwIt(S)V
					return;
			.exceptionTable {
				// start_block end_block handler_block catch_type_index
				L3 L4 L5 15;
				L7 L8 L9 15;
				L11 L12 L13 15;
				L15 L16 L17 15;
			}
		}

		.method public onCallback(BLuicc/hci/framework/HCIMessage;)V 8 {
			.stack 0;
			.locals 0;

			.descriptor	Luicc/hci/framework/HCIMessage;	1.1;

				L0:	return;
		}

	}

	.class public Api_1_Hsr_Ace_3 2 extends 0.3 {		// extends javacard/framework/Applet

		.shareable;

		.fields {
			private 5.2 rdrService 0;		// Luicc/hci/services/readermode/ReaderService;
			private static final short SW_EVENT_NOT_SUPPORTED = 28417;		// S
			private static final short SW_METHOD_NOT_SUPPORTED = 28418;		// S
			private static final byte INS_EVENT_HR_FAILED = 16;		// B
			private static final byte INS_EVENT_TARGET_DISCOVERED = 17;		// B
			private static final byte INS_EVENT_WE_DATA_RESPONSE = 18;		// B
			private static final byte INS_TM_FAILED = 19;		// B
			private static final byte INS_GET_PARAM_RESP = 20;		// B
		}

		.publicMethodTable 7 {
			equals(Ljava/lang/Object;)Z;
			register()V;
			register([BSB)V;
			selectingApplet()Z;
			deselect()V;
			getShareableInterfaceObject(Ljavacard/framework/AID;B)Ljavacard/framework/Shareable;;
			select()Z;
			process(Ljavacard/framework/APDU;)V;
			onCallback(BLuicc/hci/framework/HCIMessage;)V;
		}

		.packageMethodTable 0 {
		}

		.implementedInterfaceInfoTable { 
			.interface 0.2 { 		// javacard/framework/Shareable
			}

			.interface 1.0 { 		// uicc/hci/framework/HCIListener
				8;		// onCallback(BLuicc/hci/framework/HCIMessage;)V
			}

			.interface 5.0 { 		// uicc/hci/services/readermode/ReaderListener
				8;		// onCallback(BLuicc/hci/framework/HCIMessage;)V
			}

		}

		.method private <init>()V {
			.stack 2;
			.locals 1;

				L0:	aload_0;
					invokespecial 33;		// javacard/framework/Applet.<init>()V
					aload_0;
					invokevirtual 19;		// register()V
				L1:	aload_0;
					sconst_2;
					invokestatic 26;		// uicc/hci/framework/HCIDevice.getHCIService(S)Luicc/hci/framework/HCIService;
					checkcast 0 20;		// T_CLASSORINTERFACE uicc/hci/services/readermode/ReaderService
					putfield_a 2;		// reference uicc/hci/test/framework/api_1_hsr_ace/Api_1_Hsr_Ace_3.rdrService
					getfield_a_this 2;		// reference uicc/hci/test/framework/api_1_hsr_ace/Api_1_Hsr_Ace_3.rdrService
					aload_0;
					invokeinterface 2 20 0;		// uicc/hci/services/readermode/ReaderService
				L2:	goto L4;
				L3:	astore_1;
					sspush 27012;
					invokestatic 34;		// javacard/framework/ISOException.throwIt(S)V
				L4:	return;
			.exceptionTable {
				// start_block end_block handler_block catch_type_index
				L1 L2 L3 15;
			}
		}

		.method public static install([BSB)V 0 {
			.stack 2;
			.locals 0;

				L0:	new 22;		// uicc/hci/test/framework/api_1_hsr_ace/Api_1_Hsr_Ace_3
					dup;
					invokespecial 23;		// uicc/hci/test/framework/api_1_hsr_ace/Api_1_Hsr_Ace_3.<init>()V
					pop;
					return;
		}

		.method public process(Ljavacard/framework/APDU;)V 7 {
			.stack 2;
			.locals 2;

			.descriptor	Ljavacard/framework/APDU;	0.10;

				L0:	aload_0;
					invokevirtual 24;		// selectingApplet()Z
					ifeq L2;
				L1:	return;
				L2:	aload_1;
					invokevirtual 48;		// getBuffer()[B
					astore_2;
					aload_2;
					sconst_1;
					baload;
					stableswitch L23 16 20 L3 L7 L11 L15 L19;
				L3:	getfield_a_this 2;		// reference uicc/hci/test/framework/api_1_hsr_ace/Api_1_Hsr_Ace_3.rdrService
					bspush -126;
					invokeinterface 2 20 3;		// uicc/hci/services/readermode/ReaderService
				L4:	goto L6;
				L5:	astore_3;
					sspush 28418;
					invokestatic 34;		// javacard/framework/ISOException.throwIt(S)V
				L6:	return;
				L7:	getfield_a_this 2;		// reference uicc/hci/test/framework/api_1_hsr_ace/Api_1_Hsr_Ace_3.rdrService
					bspush 80;
					invokeinterface 2 20 3;		// uicc/hci/services/readermode/ReaderService
				L8:	goto L10;
				L9:	astore_3;
					sspush 28418;
					invokestatic 34;		// javacard/framework/ISOException.throwIt(S)V
				L10:	return;
				L11:	getfield_a_this 2;		// reference uicc/hci/test/framework/api_1_hsr_ace/Api_1_Hsr_Ace_3.rdrService
					sconst_2;
					invokeinterface 2 20 3;		// uicc/hci/services/readermode/ReaderService
				L12:	goto L14;
				L13:	astore_3;
					sspush 28418;
					invokestatic 34;		// javacard/framework/ISOException.throwIt(S)V
				L14:	return;
				L15:	getfield_a_this 2;		// reference uicc/hci/test/framework/api_1_hsr_ace/Api_1_Hsr_Ace_3.rdrService
					bspush -127;
					invokeinterface 2 20 3;		// uicc/hci/services/readermode/ReaderService
				L16:	goto L18;
				L17:	astore_3;
					sspush 28418;
					invokestatic 34;		// javacard/framework/ISOException.throwIt(S)V
				L18:	return;
				L19:	getfield_a_this 2;		// reference uicc/hci/test/framework/api_1_hsr_ace/Api_1_Hsr_Ace_3.rdrService
					sconst_1;
					invokeinterface 2 20 3;		// uicc/hci/services/readermode/ReaderService
				L20:	goto L22;
				L21:	astore_3;
					sspush 28418;
					invokestatic 34;		// javacard/framework/ISOException.throwIt(S)V
				L22:	return;
				L23:	sspush 27904;
					invokestatic 34;		// javacard/framework/ISOException.throwIt(S)V
					return;
			.exceptionTable {
				// start_block end_block handler_block catch_type_index
				L3 L4 L5 15;
				L7 L8 L9 15;
				L11 L12 L13 15;
				L15 L16 L17 15;
				L19 L20 L21 15;
			}
		}

		.method public onCallback(BLuicc/hci/framework/HCIMessage;)V 8 {
			.stack 0;
			.locals 0;

			.descriptor	Luicc/hci/framework/HCIMessage;	1.1;

				L0:	return;
		}

	}

	.class public Api_1_Hsr_Ace_4 3 extends 0.3 {		// extends javacard/framework/Applet

		.shareable;

		.fields {
			private 2.2 ceService 0;		// Luicc/hci/services/cardemulation/CardEmulationService;
			private static final short SW_METHOD_NOT_SUPPORTED = 28418;		// S
			private static final short SW_ACTIVATION_NOT_PERSISTENT = 28417;		// S
			private static final byte INS_EVENT_FIELD_OFF = 1;		// B
			private static final byte INS_CHECK_EVENT_FIELD_OFF = 2;		// B
		}

		.publicMethodTable 7 {
			equals(Ljava/lang/Object;)Z;
			register()V;
			register([BSB)V;
			selectingApplet()Z;
			deselect()V;
			getShareableInterfaceObject(Ljavacard/framework/AID;B)Ljavacard/framework/Shareable;;
			select()Z;
			process(Ljavacard/framework/APDU;)V;
			onCallback(BLuicc/hci/framework/HCIMessage;)V;
		}

		.packageMethodTable 0 {
		}

		.implementedInterfaceInfoTable { 
			.interface 0.2 { 		// javacard/framework/Shareable
			}

			.interface 1.0 { 		// uicc/hci/framework/HCIListener
				8;		// onCallback(BLuicc/hci/framework/HCIMessage;)V
			}

			.interface 2.0 { 		// uicc/hci/services/cardemulation/CardEmulationListener
				8;		// onCallback(BLuicc/hci/framework/HCIMessage;)V
			}

		}

		.method private <init>()V {
			.stack 2;
			.locals 1;

				L0:	aload_0;
					invokespecial 33;		// javacard/framework/Applet.<init>()V
					aload_0;
					invokevirtual 25;		// register()V
				L1:	aload_0;
					sconst_3;
					invokestatic 26;		// uicc/hci/framework/HCIDevice.getHCIService(S)Luicc/hci/framework/HCIService;
					checkcast 0 32;		// T_CLASSORINTERFACE uicc/hci/services/cardemulation/CardEmulationService
					putfield_a 3;		// reference uicc/hci/test/framework/api_1_hsr_ace/Api_1_Hsr_Ace_4.ceService
					getfield_a_this 3;		// reference uicc/hci/test/framework/api_1_hsr_ace/Api_1_Hsr_Ace_4.ceService
					aload_0;
					invokeinterface 2 32 0;		// uicc/hci/services/cardemulation/CardEmulationService
				L2:	goto L4;
				L3:	astore_1;
					sspush 27012;
					invokestatic 34;		// javacard/framework/ISOException.throwIt(S)V
				L4:	return;
			.exceptionTable {
				// start_block end_block handler_block catch_type_index
				L1 L2 L3 15;
			}
		}

		.method public static install([BSB)V 0 {
			.stack 2;
			.locals 0;

				L0:	new 27;		// uicc/hci/test/framework/api_1_hsr_ace/Api_1_Hsr_Ace_4
					dup;
					invokespecial 28;		// uicc/hci/test/framework/api_1_hsr_ace/Api_1_Hsr_Ace_4.<init>()V
					pop;
					return;
		}

		.method public process(Ljavacard/framework/APDU;)V 7 {
			.stack 2;
			.locals 2;

			.descriptor	Ljavacard/framework/APDU;	0.10;

				L0:	aload_0;
					invokevirtual 29;		// selectingApplet()Z
					ifeq L2;
				L1:	return;
				L2:	aload_1;
					invokevirtual 48;		// getBuffer()[B
					astore_2;
					aload_2;
					sconst_1;
					baload;
					slookupswitch L10 2 1 L3 2 L7;
				L3:	getfield_a_this 3;		// reference uicc/hci/test/framework/api_1_hsr_ace/Api_1_Hsr_Ace_4.ceService
					bspush 84;
					invokeinterface 2 32 3;		// uicc/hci/services/cardemulation/CardEmulationService
				L4:	goto L6;
				L5:	astore_3;
					sspush 28418;
					invokestatic 34;		// javacard/framework/ISOException.throwIt(S)V
				L6:	return;
				L7:	getfield_a_this 3;		// reference uicc/hci/test/framework/api_1_hsr_ace/Api_1_Hsr_Ace_4.ceService
					bspush 84;
					invokeinterface 2 32 5;		// uicc/hci/services/cardemulation/CardEmulationService
					ifne L9;
				L8:	sspush 28417;
					invokestatic 34;		// javacard/framework/ISOException.throwIt(S)V
				L9:	return;
				L10:	sspush 27904;
					invokestatic 34;		// javacard/framework/ISOException.throwIt(S)V
					return;
			.exceptionTable {
				// start_block end_block handler_block catch_type_index
				L3 L4 L5 15;
			}
		}

		.method public onCallback(BLuicc/hci/framework/HCIMessage;)V 8 {
			.stack 1;
			.locals 0;

			.descriptor	Luicc/hci/framework/HCIMessage;	1.1;

				L0:	sload_1;
					slookupswitch L1 1 80 L1;
				L1:	return;
		}

	}

	.class public Api_1_Hsr_Ace_5 4 extends 0.3 {		// extends javacard/framework/Applet

		.shareable;

		.fields {
			private 2.2 ceService 0;		// Luicc/hci/services/cardemulation/CardEmulationService;
			private byte[] ibuffer 1;		// [B
			private byte[] verificationByte 2;		// [B
			private static final short SW_EVENT_NOT_TRIGGERED = 28417;		// S
			private static final byte INS_CHECK_VB = 1;		// B
		}

		.publicMethodTable 4 {
			equals(Ljava/lang/Object;)Z;
			register()V;
			register([BSB)V;
			selectingApplet()Z;
			deselect()V;
			getShareableInterfaceObject(Ljavacard/framework/AID;B)Ljavacard/framework/Shareable;;
			select()Z;
			process(Ljavacard/framework/APDU;)V;
			onCallback(BLuicc/hci/framework/HCIMessage;)V;
		}

		.packageMethodTable 0 {
		}

		.implementedInterfaceInfoTable { 
			.interface 0.2 { 		// javacard/framework/Shareable
			}

			.interface 1.0 { 		// uicc/hci/framework/HCIListener
				8;		// onCallback(BLuicc/hci/framework/HCIMessage;)V
			}

			.interface 2.0 { 		// uicc/hci/services/cardemulation/CardEmulationListener
				8;		// onCallback(BLuicc/hci/framework/HCIMessage;)V
			}

		}

		.method private <init>()V {
			.stack 3;
			.locals 1;

				L0:	aload_0;
					invokespecial 33;		// javacard/framework/Applet.<init>()V
					aload_0;
					invokevirtual 30;		// register()V
					aload_0;
					sconst_2;
					sconst_1;
					invokestatic 31;		// javacard/framework/JCSystem.makeTransientByteArray(SB)[B
					putfield_a 4;		// reference uicc/hci/test/framework/api_1_hsr_ace/Api_1_Hsr_Ace_5.ibuffer
					aload_0;
					sconst_1;
					newarray 11;
					putfield_a 5;		// reference uicc/hci/test/framework/api_1_hsr_ace/Api_1_Hsr_Ace_5.verificationByte
					getfield_a_this 5;		// reference uicc/hci/test/framework/api_1_hsr_ace/Api_1_Hsr_Ace_5.verificationByte
					sconst_0;
					sconst_0;
					bastore;
				L1:	aload_0;
					sconst_3;
					invokestatic 26;		// uicc/hci/framework/HCIDevice.getHCIService(S)Luicc/hci/framework/HCIService;
					checkcast 0 32;		// T_CLASSORINTERFACE uicc/hci/services/cardemulation/CardEmulationService
					putfield_a 6;		// reference uicc/hci/test/framework/api_1_hsr_ace/Api_1_Hsr_Ace_5.ceService
					getfield_a_this 6;		// reference uicc/hci/test/framework/api_1_hsr_ace/Api_1_Hsr_Ace_5.ceService
					aload_0;
					invokeinterface 2 32 0;		// uicc/hci/services/cardemulation/CardEmulationService
					getfield_a_this 6;		// reference uicc/hci/test/framework/api_1_hsr_ace/Api_1_Hsr_Ace_5.ceService
					bspush 80;
					invokeinterface 2 32 3;		// uicc/hci/services/cardemulation/CardEmulationService
				L2:	goto L4;
				L3:	astore_1;
					sspush 27012;
					invokestatic 34;		// javacard/framework/ISOException.throwIt(S)V
				L4:	return;
			.exceptionTable {
				// start_block end_block handler_block catch_type_index
				L1 L2 L3 15;
			}
		}

		.method public static install([BSB)V 0 {
			.stack 2;
			.locals 0;

				L0:	new 35;		// uicc/hci/test/framework/api_1_hsr_ace/Api_1_Hsr_Ace_5
					dup;
					invokespecial 36;		// uicc/hci/test/framework/api_1_hsr_ace/Api_1_Hsr_Ace_5.<init>()V
					pop;
					return;
		}

		.method public process(Ljavacard/framework/APDU;)V 7 {
			.stack 2;
			.locals 1;

			.descriptor	Ljavacard/framework/APDU;	0.10;

				L0:	aload_0;
					invokevirtual 37;		// selectingApplet()Z
					ifeq L2;
				L1:	return;
				L2:	aload_1;
					invokevirtual 48;		// getBuffer()[B
					astore_2;
					aload_2;
					sconst_1;
					baload;
					slookupswitch L6 1 1 L3;
				L3:	getfield_a_this 5;		// reference uicc/hci/test/framework/api_1_hsr_ace/Api_1_Hsr_Ace_5.verificationByte
					sconst_0;
					baload;
					sconst_1;
					sand;
					sconst_1;
					if_scmpeq L5;
				L4:	sspush 28417;
					invokestatic 34;		// javacard/framework/ISOException.throwIt(S)V
				L5:	return;
				L6:	sspush 27904;
					invokestatic 34;		// javacard/framework/ISOException.throwIt(S)V
					return;
		}

		.method public deselect()V 4 {
			.stack 4;
			.locals 0;

				L0:	getfield_a_this 5;		// reference uicc/hci/test/framework/api_1_hsr_ace/Api_1_Hsr_Ace_5.verificationByte
					sconst_0;
					dup2;
					baload;
					sconst_2;
					sor;
					bastore;
					aload_0;
					invokespecial 38;		// super(uicc/hci/test/framework/api_1_hsr_ace/Api_1_Hsr_Ace_5).deselect()V
					return;
		}

		.method public onCallback(BLuicc/hci/framework/HCIMessage;)V 8 {
			.stack 4;
			.locals 1;

			.descriptor	Luicc/hci/framework/HCIMessage;	1.1;

				L0:	aload_2;
					checkcast 0 39;		// T_CLASSORINTERFACE uicc/hci/services/cardemulation/CardEmulationMessage
					astore_3;
					sload_1;
					slookupswitch L5 2 80 L1 84 L2;
				L1:	getfield_a_this 4;		// reference uicc/hci/test/framework/api_1_hsr_ace/Api_1_Hsr_Ace_5.ibuffer
					sconst_0;
					bspush -112;
					bastore;
					getfield_a_this 4;		// reference uicc/hci/test/framework/api_1_hsr_ace/Api_1_Hsr_Ace_5.ibuffer
					sconst_1;
					sconst_0;
					bastore;
					aload_3;
					getfield_a_this 4;		// reference uicc/hci/test/framework/api_1_hsr_ace/Api_1_Hsr_Ace_5.ibuffer
					sconst_0;
					sconst_2;
					invokeinterface 4 39 8;		// uicc/hci/services/cardemulation/CardEmulationMessage
					return;
				L2:	getfield_a_this 5;		// reference uicc/hci/test/framework/api_1_hsr_ace/Api_1_Hsr_Ace_5.verificationByte
					sconst_0;
					baload;
					sconst_2;
					sand;
					ifne L4;
				L3:	getfield_a_this 5;		// reference uicc/hci/test/framework/api_1_hsr_ace/Api_1_Hsr_Ace_5.verificationByte
					sconst_0;
					dup2;
					baload;
					sconst_1;
					sor;
					bastore;
				L4:	getfield_a_this 6;		// reference uicc/hci/test/framework/api_1_hsr_ace/Api_1_Hsr_Ace_5.ceService
					bspush 80;
					invokeinterface 2 32 4;		// uicc/hci/services/cardemulation/CardEmulationService
				L5:	return;
		}

	}

	.class public Api_1_Hsr_Ace_6 5 extends 0.3 {		// extends javacard/framework/Applet

		.shareable;

		.fields {
			private 2.2 ceService 0;		// Luicc/hci/services/cardemulation/CardEmulationService;
			private byte[] ibuffer 1;		// [B
			private byte[] verificationByte 2;		// [B
		}

		.publicMethodTable 7 {
			equals(Ljava/lang/Object;)Z;
			register()V;
			register([BSB)V;
			selectingApplet()Z;
			deselect()V;
			getShareableInterfaceObject(Ljavacard/framework/AID;B)Ljavacard/framework/Shareable;;
			select()Z;
			process(Ljavacard/framework/APDU;)V;
			onCallback(BLuicc/hci/framework/HCIMessage;)V;
		}

		.packageMethodTable 0 {
		}

		.implementedInterfaceInfoTable { 
			.interface 0.2 { 		// javacard/framework/Shareable
			}

			.interface 1.0 { 		// uicc/hci/framework/HCIListener
				8;		// onCallback(BLuicc/hci/framework/HCIMessage;)V
			}

			.interface 2.0 { 		// uicc/hci/services/cardemulation/CardEmulationListener
				8;		// onCallback(BLuicc/hci/framework/HCIMessage;)V
			}

		}

		.method private <init>()V {
			.stack 3;
			.locals 1;

				L0:	aload_0;
					invokespecial 33;		// javacard/framework/Applet.<init>()V
					aload_0;
					invokevirtual 40;		// register()V
					aload_0;
					sconst_1;
					newarray 11;
					putfield_a 7;		// reference uicc/hci/test/framework/api_1_hsr_ace/Api_1_Hsr_Ace_6.verificationByte
					getfield_a_this 7;		// reference uicc/hci/test/framework/api_1_hsr_ace/Api_1_Hsr_Ace_6.verificationByte
					sconst_0;
					sconst_0;
					bastore;
					aload_0;
					sconst_5;
					sconst_1;
					invokestatic 31;		// javacard/framework/JCSystem.makeTransientByteArray(SB)[B
					putfield_a 8;		// reference uicc/hci/test/framework/api_1_hsr_ace/Api_1_Hsr_Ace_6.ibuffer
				L1:	aload_0;
					sconst_3;
					invokestatic 26;		// uicc/hci/framework/HCIDevice.getHCIService(S)Luicc/hci/framework/HCIService;
					checkcast 0 32;		// T_CLASSORINTERFACE uicc/hci/services/cardemulation/CardEmulationService
					putfield_a 9;		// reference uicc/hci/test/framework/api_1_hsr_ace/Api_1_Hsr_Ace_6.ceService
					getfield_a_this 9;		// reference uicc/hci/test/framework/api_1_hsr_ace/Api_1_Hsr_Ace_6.ceService
					aload_0;
					invokeinterface 2 32 0;		// uicc/hci/services/cardemulation/CardEmulationService
					getfield_a_this 9;		// reference uicc/hci/test/framework/api_1_hsr_ace/Api_1_Hsr_Ace_6.ceService
					bspush 80;
					invokeinterface 2 32 3;		// uicc/hci/services/cardemulation/CardEmulationService
					getfield_a_this 9;		// reference uicc/hci/test/framework/api_1_hsr_ace/Api_1_Hsr_Ace_6.ceService
					bspush 84;
					invokeinterface 2 32 3;		// uicc/hci/services/cardemulation/CardEmulationService
				L2:	goto L4;
				L3:	astore_1;
					sspush 27012;
					invokestatic 34;		// javacard/framework/ISOException.throwIt(S)V
				L4:	return;
			.exceptionTable {
				// start_block end_block handler_block catch_type_index
				L1 L2 L3 15;
			}
		}

		.method public static install([BSB)V 0 {
			.stack 2;
			.locals 0;

				L0:	new 44;		// uicc/hci/test/framework/api_1_hsr_ace/Api_1_Hsr_Ace_6
					dup;
					invokespecial 45;		// uicc/hci/test/framework/api_1_hsr_ace/Api_1_Hsr_Ace_6.<init>()V
					pop;
					return;
		}

		.method public process(Ljavacard/framework/APDU;)V 7 {
			.stack 2;
			.locals 1;

			.descriptor	Ljavacard/framework/APDU;	0.10;

				L0:	aload_0;
					invokevirtual 46;		// selectingApplet()Z
					ifeq L2;
				L1:	return;
				L2:	aload_1;
					invokevirtual 48;		// getBuffer()[B
					astore_2;
					aload_2;
					sconst_1;
					baload;
					slookupswitch L3 0;
				L3:	sspush 27904;
					invokestatic 34;		// javacard/framework/ISOException.throwIt(S)V
					return;
		}

		.method public onCallback(BLuicc/hci/framework/HCIMessage;)V 8 {
			.stack 4;
			.locals 1;

			.descriptor	Luicc/hci/framework/HCIMessage;	1.1;

				L0:	getfield_a_this 8;		// reference uicc/hci/test/framework/api_1_hsr_ace/Api_1_Hsr_Ace_6.ibuffer
					sconst_0;
					bspush -112;
					bastore;
					getfield_a_this 8;		// reference uicc/hci/test/framework/api_1_hsr_ace/Api_1_Hsr_Ace_6.ibuffer
					sconst_1;
					sconst_0;
					bastore;
					aload_2;
					checkcast 0 39;		// T_CLASSORINTERFACE uicc/hci/services/cardemulation/CardEmulationMessage
					astore_3;
					sload_1;
					slookupswitch L2 1 84 L1;
				L1:	getfield_a_this 7;		// reference uicc/hci/test/framework/api_1_hsr_ace/Api_1_Hsr_Ace_6.verificationByte
					sconst_0;
					dup2;
					baload;
					sconst_1;
					sor;
					bastore;
					return;
				L2:	getfield_a_this 7;		// reference uicc/hci/test/framework/api_1_hsr_ace/Api_1_Hsr_Ace_6.verificationByte
					sconst_0;
					baload;
					sconst_1;
					sand;
					sconst_1;
					if_scmpne L4;
				L3:	getfield_a_this 8;		// reference uicc/hci/test/framework/api_1_hsr_ace/Api_1_Hsr_Ace_6.ibuffer
					sconst_0;
					bspush 106;
					bastore;
					getfield_a_this 8;		// reference uicc/hci/test/framework/api_1_hsr_ace/Api_1_Hsr_Ace_6.ibuffer
					sconst_1;
					bspush -128;
					bastore;
				L4:	aload_3;
					getfield_a_this 8;		// reference uicc/hci/test/framework/api_1_hsr_ace/Api_1_Hsr_Ace_6.ibuffer
					sconst_0;
					sconst_2;
					invokeinterface 4 39 8;		// uicc/hci/services/cardemulation/CardEmulationMessage
					return;
		}

	}

	.class public Api_1_Hsr_Ace_7 6 extends 0.3 {		// extends javacard/framework/Applet

		.shareable;

		.fields {
			private 5.2 rdrService 0;		// Luicc/hci/services/readermode/ReaderService;
			private static final byte INS_HCI_DISABLED = 1;		// B
			private static final short SW_UNKNOWN_PROP = 28417;		// S
		}

		.publicMethodTable 7 {
			equals(Ljava/lang/Object;)Z;
			register()V;
			register([BSB)V;
			selectingApplet()Z;
			deselect()V;
			getShareableInterfaceObject(Ljavacard/framework/AID;B)Ljavacard/framework/Shareable;;
			select()Z;
			process(Ljavacard/framework/APDU;)V;
			onCallback(BLuicc/hci/framework/HCIMessage;)V;
		}

		.packageMethodTable 0 {
		}

		.implementedInterfaceInfoTable { 
			.interface 0.2 { 		// javacard/framework/Shareable
			}

			.interface 1.0 { 		// uicc/hci/framework/HCIListener
				8;		// onCallback(BLuicc/hci/framework/HCIMessage;)V
			}

			.interface 5.0 { 		// uicc/hci/services/readermode/ReaderListener
				8;		// onCallback(BLuicc/hci/framework/HCIMessage;)V
			}

		}

		.method private <init>()V {
			.stack 2;
			.locals 1;

				L0:	aload_0;
					invokespecial 33;		// javacard/framework/Applet.<init>()V
					aload_0;
					invokevirtual 47;		// register()V
				L1:	aload_0;
					sconst_2;
					invokestatic 26;		// uicc/hci/framework/HCIDevice.getHCIService(S)Luicc/hci/framework/HCIService;
					checkcast 0 20;		// T_CLASSORINTERFACE uicc/hci/services/readermode/ReaderService
					putfield_a 10;		// reference uicc/hci/test/framework/api_1_hsr_ace/Api_1_Hsr_Ace_7.rdrService
					getfield_a_this 10;		// reference uicc/hci/test/framework/api_1_hsr_ace/Api_1_Hsr_Ace_7.rdrService
					aload_0;
					invokeinterface 2 20 0;		// uicc/hci/services/readermode/ReaderService
				L2:	goto L4;
				L3:	astore_1;
					sspush 27012;
					invokestatic 34;		// javacard/framework/ISOException.throwIt(S)V
				L4:	return;
			.exceptionTable {
				// start_block end_block handler_block catch_type_index
				L1 L2 L3 15;
			}
		}

		.method public static install([BSB)V 0 {
			.stack 2;
			.locals 0;

				L0:	new 49;		// uicc/hci/test/framework/api_1_hsr_ace/Api_1_Hsr_Ace_7
					dup;
					invokespecial 50;		// uicc/hci/test/framework/api_1_hsr_ace/Api_1_Hsr_Ace_7.<init>()V
					pop;
					return;
		}

		.method public process(Ljavacard/framework/APDU;)V 7 {
			.stack 2;
			.locals 2;

			.descriptor	Ljavacard/framework/APDU;	0.10;

				L0:	aload_0;
					invokevirtual 51;		// selectingApplet()Z
					ifeq L2;
				L1:	return;
				L2:	aload_1;
					invokevirtual 48;		// getBuffer()[B
					astore_2;
					aload_2;
					sconst_1;
					baload;
					slookupswitch L8 1 1 L3;
				L3:	getfield_a_this 10;		// reference uicc/hci/test/framework/api_1_hsr_ace/Api_1_Hsr_Ace_7.rdrService
					bspush 80;
					invokeinterface 2 20 3;		// uicc/hci/services/readermode/ReaderService
				L4:	goto L7;
				L5:	astore_3;
					aload_3;
					invokevirtual 53;		// getReason()S
					sconst_3;
					if_scmpne L7;
				L6:	return;
				L7:	sspush 28417;
					invokestatic 34;		// javacard/framework/ISOException.throwIt(S)V
				L8:	sspush 27904;
					invokestatic 34;		// javacard/framework/ISOException.throwIt(S)V
					return;
			.exceptionTable {
				// start_block end_block handler_block catch_type_index
				L3 L4 L5 15;
			}
		}

		.method public onCallback(BLuicc/hci/framework/HCIMessage;)V 8 {
			.stack 0;
			.locals 0;

			.descriptor	Luicc/hci/framework/HCIMessage;	1.1;

				L0:	return;
		}

	}

	.class public Api_1_Hsr_Ace_8 7 extends 0.3 {		// extends javacard/framework/Applet

		.shareable;

		.fields {
			private 2.2 ceService 0;		// Luicc/hci/services/cardemulation/CardEmulationService;
			private byte verificationByte 1;		// B
			private static final short SW_METHOD_NOT_SUPPORTED = 28417;		// S
			private static final byte INS_VERIFY = 1;		// B
		}

		.publicMethodTable 6 {
			equals(Ljava/lang/Object;)Z;
			register()V;
			register([BSB)V;
			selectingApplet()Z;
			deselect()V;
			getShareableInterfaceObject(Ljavacard/framework/AID;B)Ljavacard/framework/Shareable;;
			select()Z;
			process(Ljavacard/framework/APDU;)V;
			onCallback(BLuicc/hci/framework/HCIMessage;)V;
		}

		.packageMethodTable 0 {
		}

		.implementedInterfaceInfoTable { 
			.interface 0.2 { 		// javacard/framework/Shareable
			}

			.interface 1.0 { 		// uicc/hci/framework/HCIListener
				8;		// onCallback(BLuicc/hci/framework/HCIMessage;)V
			}

			.interface 2.0 { 		// uicc/hci/services/cardemulation/CardEmulationListener
				8;		// onCallback(BLuicc/hci/framework/HCIMessage;)V
			}

		}

		.method private <init>()V {
			.stack 2;
			.locals 1;

				L0:	aload_0;
					invokespecial 33;		// javacard/framework/Applet.<init>()V
					aload_0;
					invokevirtual 52;		// register()V
					aload_0;
					sconst_0;
					putfield_b 11;		// byte uicc/hci/test/framework/api_1_hsr_ace/Api_1_Hsr_Ace_8.verificationByte
				L1:	aload_0;
					sconst_3;
					invokestatic 26;		// uicc/hci/framework/HCIDevice.getHCIService(S)Luicc/hci/framework/HCIService;
					checkcast 0 32;		// T_CLASSORINTERFACE uicc/hci/services/cardemulation/CardEmulationService
					putfield_a 12;		// reference uicc/hci/test/framework/api_1_hsr_ace/Api_1_Hsr_Ace_8.ceService
					getfield_a_this 12;		// reference uicc/hci/test/framework/api_1_hsr_ace/Api_1_Hsr_Ace_8.ceService
					aload_0;
					invokeinterface 2 32 0;		// uicc/hci/services/cardemulation/CardEmulationService
				L2:	goto L4;
				L3:	astore_1;
					sspush 27012;
					invokestatic 34;		// javacard/framework/ISOException.throwIt(S)V
				L4:	return;
			.exceptionTable {
				// start_block end_block handler_block catch_type_index
				L1 L2 L3 15;
			}
		}

		.method public static install([BSB)V 0 {
			.stack 2;
			.locals 0;

				L0:	new 55;		// uicc/hci/test/framework/api_1_hsr_ace/Api_1_Hsr_Ace_8
					dup;
					invokespecial 56;		// uicc/hci/test/framework/api_1_hsr_ace/Api_1_Hsr_Ace_8.<init>()V
					pop;
					return;
		}

		.method public process(Ljavacard/framework/APDU;)V 7 {
			.stack 3;
			.locals 1;

			.descriptor	Ljavacard/framework/APDU;	0.10;

				L0:	aload_0;
					invokevirtual 57;		// selectingApplet()Z
					ifeq L2;
				L1:	return;
				L2:	aload_1;
					invokevirtual 48;		// getBuffer()[B
					astore_2;
					aload_2;
					sconst_1;
					baload;
					slookupswitch L6 1 1 L3;
				L3:	getfield_b_this 11;		// byte uicc/hci/test/framework/api_1_hsr_ace/Api_1_Hsr_Ace_8.verificationByte
					sconst_1;
					if_scmpeq L5;
				L4:	sspush 28417;
					invokestatic 34;		// javacard/framework/ISOException.throwIt(S)V
				L5:	return;
				L6:	sspush 27904;
					invokestatic 34;		// javacard/framework/ISOException.throwIt(S)V
					aload_1;
					sconst_0;
					sconst_0;
					invokevirtual 54;		// setOutgoingAndSend(SS)V
					return;
		}

		.method public onCallback(BLuicc/hci/framework/HCIMessage;)V 8 {
			.stack 0;
			.locals 0;

			.descriptor	Luicc/hci/framework/HCIMessage;	1.1;

				L0:	return;
		}

		.method public select()Z 6 {
			.stack 2;
			.locals 0;

				L0:	aload_0;
					sconst_1;
					putfield_b 11;		// byte uicc/hci/test/framework/api_1_hsr_ace/Api_1_Hsr_Ace_8.verificationByte
					aload_0;
					invokespecial 58;		// super(uicc/hci/test/framework/api_1_hsr_ace/Api_1_Hsr_Ace_8).select()Z
					sreturn;
		}

	}

	.class public Api_1_Hsr_Ace_9 8 extends 0.3 {		// extends javacard/framework/Applet

		.shareable;

		.fields {
			private 5.2 rdrService 0;		// Luicc/hci/services/readermode/ReaderService;
			private static final byte INS_HCI_DISABLED = 1;		// B
			private static final short SW_UNKNOWN_PROP = 28417;		// S
		}

		.publicMethodTable 7 {
			equals(Ljava/lang/Object;)Z;
			register()V;
			register([BSB)V;
			selectingApplet()Z;
			deselect()V;
			getShareableInterfaceObject(Ljavacard/framework/AID;B)Ljavacard/framework/Shareable;;
			select()Z;
			process(Ljavacard/framework/APDU;)V;
			onCallback(BLuicc/hci/framework/HCIMessage;)V;
			uninstall()V;
		}

		.packageMethodTable 0 {
		}

		.implementedInterfaceInfoTable { 
			.interface 0.2 { 		// javacard/framework/Shareable
			}

			.interface 1.0 { 		// uicc/hci/framework/HCIListener
				8;		// onCallback(BLuicc/hci/framework/HCIMessage;)V
			}

			.interface 5.0 { 		// uicc/hci/services/readermode/ReaderListener
				8;		// onCallback(BLuicc/hci/framework/HCIMessage;)V
			}

		}

		.method private <init>()V {
			.stack 2;
			.locals 1;

				L0:	aload_0;
					invokespecial 33;		// javacard/framework/Applet.<init>()V
					aload_0;
					invokevirtual 59;		// register()V
				L1:	aload_0;
					sconst_2;
					invokestatic 26;		// uicc/hci/framework/HCIDevice.getHCIService(S)Luicc/hci/framework/HCIService;
					checkcast 0 20;		// T_CLASSORINTERFACE uicc/hci/services/readermode/ReaderService
					putfield_a 13;		// reference uicc/hci/test/framework/api_1_hsr_ace/Api_1_Hsr_Ace_9.rdrService
					getfield_a_this 13;		// reference uicc/hci/test/framework/api_1_hsr_ace/Api_1_Hsr_Ace_9.rdrService
					aload_0;
					invokeinterface 2 20 0;		// uicc/hci/services/readermode/ReaderService
				L2:	goto L4;
				L3:	astore_1;
					sspush 27012;
					invokestatic 34;		// javacard/framework/ISOException.throwIt(S)V
				L4:	return;
			.exceptionTable {
				// start_block end_block handler_block catch_type_index
				L1 L2 L3 15;
			}
		}

		.method public static install([BSB)V 0 {
			.stack 2;
			.locals 0;

				L0:	new 61;		// uicc/hci/test/framework/api_1_hsr_ace/Api_1_Hsr_Ace_9
					dup;
					invokespecial 62;		// uicc/hci/test/framework/api_1_hsr_ace/Api_1_Hsr_Ace_9.<init>()V
					pop;
					return;
		}

		.method public process(Ljavacard/framework/APDU;)V 7 {
			.stack 2;
			.locals 2;

			.descriptor	Ljavacard/framework/APDU;	0.10;

				L0:	aload_0;
					invokevirtual 63;		// selectingApplet()Z
					ifeq L2;
				L1:	return;
				L2:	aload_1;
					invokevirtual 48;		// getBuffer()[B
					astore_2;
					aload_2;
					sconst_1;
					baload;
					slookupswitch L9 1 1 L3;
				L3:	sconst_1;
					sconst_0;
					invokestatic 64;		// org/globalplatform/contactless/GPCLSystem.setCommunicationInterface(SZ)V
				L4:	getfield_a_this 13;		// reference uicc/hci/test/framework/api_1_hsr_ace/Api_1_Hsr_Ace_9.rdrService
					bspush 80;
					invokeinterface 2 20 3;		// uicc/hci/services/readermode/ReaderService
				L5:	goto L8;
				L6:	astore_3;
					aload_3;
					invokevirtual 53;		// getReason()S
					sconst_3;
					if_scmpne L8;
				L7:	return;
				L8:	sspush 28417;
					invokestatic 34;		// javacard/framework/ISOException.throwIt(S)V
				L9:	sspush 27904;
					invokestatic 34;		// javacard/framework/ISOException.throwIt(S)V
					return;
			.exceptionTable {
				// start_block end_block handler_block catch_type_index
				L4 L5 L6 15;
			}
		}

		.method public onCallback(BLuicc/hci/framework/HCIMessage;)V 8 {
			.stack 0;
			.locals 0;

			.descriptor	Luicc/hci/framework/HCIMessage;	1.1;

				L0:	return;
		}

		.method public uninstall()V 9 {
			.stack 2;
			.locals 0;

				L0:	sconst_1;
					sconst_1;
					invokestatic 64;		// org/globalplatform/contactless/GPCLSystem.setCommunicationInterface(SZ)V
					return;
		}

	}

}
