// converted by version  [v3.0.2]
// on Fri Nov 08 11:48:57 CET 2013

.package uicc/hci/test/framework/api_1_hdv_isa {
	.aid 0xA0:0x0:0x0:0x0:0x9:0x0:0x5:0xFF:0xFF:0xFF:0xFF:0x89:0x21:0x0:0x0:0x0;
	.version 1.0;

	.imports {
		0xA0:0x0:0x0:0x0:0x62:0x1:0x1 1.4;		//javacard/framework
		0xA0:0x0:0x0:0x0:0x9:0x0:0x5:0xFF:0xFF:0xFF:0xFF:0x89:0x16:0x1:0x0:0x0 1.0;		//uicc/hci/framework
		0xA0:0x0:0x0:0x0:0x9:0x0:0x5:0xFF:0xFF:0xFF:0xFF:0x89:0x16:0x2:0x1:0x0 1.0;		//uicc/hci/services/cardemulation
		0xA0:0x0:0x0:0x0:0x62:0x0:0x1 1.0;		//java/lang
		0xA0:0x0:0x0:0x1:0x51:0x2 1.0;		//org/globalplatform/contactless
	}

	.applet {
		0xA0:0x0:0x0:0x0:0x9:0x0:0x5:0xFF:0xFF:0xFF:0xFF:0x89:0x21:0x3:0x1:0x2 Api_1_Hdv_Isa_1;
		0xA0:0x0:0x0:0x0:0x9:0x0:0x5:0xFF:0xFF:0xFF:0xFF:0x89:0x21:0x3:0x2:0x2 Api_1_Hdv_Isa_2;
		0xA0:0x0:0x0:0x0:0x9:0x0:0x5:0xFF:0xFF:0xFF:0xFF:0x89:0x21:0x3:0x3:0x2 Api_1_Hdv_Isa_3;
	}

	.constantPool {
		// 0
		staticMethodRef 0.3.0()V;		// javacard/framework/Applet.<init>()V
		// 1
		virtualMethodRef 0.3.1()V;		// register()V
		// 2
		.classRef Api_1_Hdv_Isa_1;
		// 3
		staticMethodRef Api_1_Hdv_Isa_1/<init>()V;
		// 4
		virtualMethodRef 0.3.3()Z;		// selectingApplet()Z
		// 5
		virtualMethodRef 0.10.1()[B;		// getBuffer()[B
		// 6
		staticMethodRef 1.4.2(S)B;		// uicc/hci/framework/HCIDevice.isHCIServiceAvailable(S)B
		// 7
		staticMethodRef 0.7.1(S)V;		// javacard/framework/ISOException.throwIt(S)V
		// 8
		virtualMethodRef 0.10.8(SS)V;		// setOutgoingAndSend(SS)V
		// 9
		virtualMethodRef 0.3.1()V;		// register()V
		// 10
		.classRef Api_1_Hdv_Isa_2;
		// 11
		staticMethodRef Api_1_Hdv_Isa_2/<init>()V;
		// 12
		virtualMethodRef 0.3.3()Z;		// selectingApplet()Z
		// 13
		virtualMethodRef 0.3.1()V;		// register()V
		// 14
		.classRef Api_1_Hdv_Isa_3;
		// 15
		staticMethodRef Api_1_Hdv_Isa_3/<init>()V;
		// 16
		virtualMethodRef 0.3.3()Z;		// selectingApplet()Z
		// 17
		staticMethodRef 4.5.4(SZ)V;		// org/globalplatform/contactless/GPCLSystem.setCommunicationInterface(SZ)V
	}

	.class public Api_1_Hdv_Isa_1 0 extends 0.3 {		// extends javacard/framework/Applet

		.shareable;

		.fields {
			private static final short INS_CEM_SERVICE_AVAILABLE = 6;		// S
			private static final short INS_CNN_SERVICE_AVAILABLE = 7;		// S
			private static final short INS_RS_SERVICE_AVAILABLE = 8;		// S
		}

		.publicMethodTable 7 {
			equals(Ljava/lang/Object;)Z;
			register()V;
			register([BSB)V;
			selectingApplet()Z;
			deselect()V;
			getShareableInterfaceObject(Ljavacard/framework/AID;B)Ljavacard/framework/Shareable;;
			select()Z;
			process(Ljavacard/framework/APDU;)V;
			onCallback(BLuicc/hci/framework/HCIMessage;)V;
		}

		.packageMethodTable 0 {
		}

		.implementedInterfaceInfoTable { 
			.interface 0.2 { 		// javacard/framework/Shareable
			}

			.interface 1.0 { 		// uicc/hci/framework/HCIListener
				8;		// onCallback(BLuicc/hci/framework/HCIMessage;)V
			}

			.interface 2.0 { 		// uicc/hci/services/cardemulation/CardEmulationListener
				8;		// onCallback(BLuicc/hci/framework/HCIMessage;)V
			}

		}

		.method private <init>()V {
			.stack 1;
			.locals 0;

				L0:	aload_0;
					invokespecial 0;		// javacard/framework/Applet.<init>()V
					aload_0;
					invokevirtual 1;		// register()V
					return;
		}

		.method public static install([BSB)V 0 {
			.stack 2;
			.locals 0;

				L0:	new 2;		// uicc/hci/test/framework/api_1_hdv_isa/Api_1_Hdv_Isa_1
					dup;
					invokespecial 3;		// uicc/hci/test/framework/api_1_hdv_isa/Api_1_Hdv_Isa_1.<init>()V
					pop;
					return;
		}

		.method public process(Ljavacard/framework/APDU;)V 7 {
			.stack 3;
			.locals 1;

			.descriptor	Ljavacard/framework/APDU;	0.10;

				L0:	aload_0;
					invokevirtual 4;		// selectingApplet()Z
					ifeq L2;
				L1:	return;
				L2:	aload_1;
					invokevirtual 5;		// getBuffer()[B
					astore_2;
					aload_2;
					sconst_1;
					baload;
					stableswitch L6 6 8 L3 L4 L5;
				L3:	aload_2;
					sconst_2;
					sconst_3;
					invokestatic 6;		// uicc/hci/framework/HCIDevice.isHCIServiceAvailable(S)B
					bastore;
					goto L7;
				L4:	aload_2;
					sconst_2;
					sconst_4;
					invokestatic 6;		// uicc/hci/framework/HCIDevice.isHCIServiceAvailable(S)B
					bastore;
					goto L7;
				L5:	aload_2;
					sconst_2;
					sconst_2;
					invokestatic 6;		// uicc/hci/framework/HCIDevice.isHCIServiceAvailable(S)B
					bastore;
					goto L7;
				L6:	sspush 27904;
					invokestatic 7;		// javacard/framework/ISOException.throwIt(S)V
				L7:	aload_1;
					sconst_2;
					sconst_1;
					invokevirtual 8;		// setOutgoingAndSend(SS)V
					return;
		}

		.method public onCallback(BLuicc/hci/framework/HCIMessage;)V 8 {
			.stack 0;
			.locals 0;

			.descriptor	Luicc/hci/framework/HCIMessage;	1.1;

				L0:	return;
		}

	}

	.class public Api_1_Hdv_Isa_2 1 extends 0.3 {		// extends javacard/framework/Applet

		.shareable;

		.fields {
			private static final short INS_CEM_SERVICE_AVAILABLE = 6;		// S
		}

		.publicMethodTable 7 {
			equals(Ljava/lang/Object;)Z;
			register()V;
			register([BSB)V;
			selectingApplet()Z;
			deselect()V;
			getShareableInterfaceObject(Ljavacard/framework/AID;B)Ljavacard/framework/Shareable;;
			select()Z;
			process(Ljavacard/framework/APDU;)V;
			onCallback(BLuicc/hci/framework/HCIMessage;)V;
		}

		.packageMethodTable 0 {
		}

		.implementedInterfaceInfoTable { 
			.interface 0.2 { 		// javacard/framework/Shareable
			}

			.interface 1.0 { 		// uicc/hci/framework/HCIListener
				8;		// onCallback(BLuicc/hci/framework/HCIMessage;)V
			}

			.interface 2.0 { 		// uicc/hci/services/cardemulation/CardEmulationListener
				8;		// onCallback(BLuicc/hci/framework/HCIMessage;)V
			}

		}

		.method private <init>()V {
			.stack 1;
			.locals 0;

				L0:	aload_0;
					invokespecial 0;		// javacard/framework/Applet.<init>()V
					aload_0;
					invokevirtual 9;		// register()V
					return;
		}

		.method public static install([BSB)V 0 {
			.stack 2;
			.locals 0;

				L0:	new 10;		// uicc/hci/test/framework/api_1_hdv_isa/Api_1_Hdv_Isa_2
					dup;
					invokespecial 11;		// uicc/hci/test/framework/api_1_hdv_isa/Api_1_Hdv_Isa_2.<init>()V
					pop;
					return;
		}

		.method public process(Ljavacard/framework/APDU;)V 7 {
			.stack 3;
			.locals 1;

			.descriptor	Ljavacard/framework/APDU;	0.10;

				L0:	aload_0;
					invokevirtual 12;		// selectingApplet()Z
					ifeq L2;
				L1:	return;
				L2:	aload_1;
					invokevirtual 5;		// getBuffer()[B
					astore_2;
					aload_2;
					sconst_1;
					baload;
					slookupswitch L4 1 6 L3;
				L3:	aload_2;
					sconst_2;
					sconst_3;
					invokestatic 6;		// uicc/hci/framework/HCIDevice.isHCIServiceAvailable(S)B
					bastore;
					goto L5;
				L4:	sspush 27904;
					invokestatic 7;		// javacard/framework/ISOException.throwIt(S)V
				L5:	aload_1;
					sconst_2;
					sconst_1;
					invokevirtual 8;		// setOutgoingAndSend(SS)V
					return;
		}

		.method public onCallback(BLuicc/hci/framework/HCIMessage;)V 8 {
			.stack 0;
			.locals 0;

			.descriptor	Luicc/hci/framework/HCIMessage;	1.1;

				L0:	return;
		}

	}

	.class public Api_1_Hdv_Isa_3 2 extends 0.3 {		// extends javacard/framework/Applet

		.shareable;

		.fields {
			private static final short INS_CEM_SERVICE_AVAILABLE = 6;		// S
		}

		.publicMethodTable 7 {
			equals(Ljava/lang/Object;)Z;
			register()V;
			register([BSB)V;
			selectingApplet()Z;
			deselect()V;
			getShareableInterfaceObject(Ljavacard/framework/AID;B)Ljavacard/framework/Shareable;;
			select()Z;
			process(Ljavacard/framework/APDU;)V;
			onCallback(BLuicc/hci/framework/HCIMessage;)V;
			uninstall()V;
		}

		.packageMethodTable 0 {
		}

		.implementedInterfaceInfoTable { 
			.interface 0.2 { 		// javacard/framework/Shareable
			}

			.interface 1.0 { 		// uicc/hci/framework/HCIListener
				8;		// onCallback(BLuicc/hci/framework/HCIMessage;)V
			}

			.interface 2.0 { 		// uicc/hci/services/cardemulation/CardEmulationListener
				8;		// onCallback(BLuicc/hci/framework/HCIMessage;)V
			}

			.interface 0.18 { 		// javacard/framework/AppletEvent
				9;		// uninstall()V
			}

		}

		.method private <init>()V {
			.stack 1;
			.locals 0;

				L0:	aload_0;
					invokespecial 0;		// javacard/framework/Applet.<init>()V
					aload_0;
					invokevirtual 13;		// register()V
					return;
		}

		.method public static install([BSB)V 0 {
			.stack 2;
			.locals 0;

				L0:	new 14;		// uicc/hci/test/framework/api_1_hdv_isa/Api_1_Hdv_Isa_3
					dup;
					invokespecial 15;		// uicc/hci/test/framework/api_1_hdv_isa/Api_1_Hdv_Isa_3.<init>()V
					pop;
					return;
		}

		.method public process(Ljavacard/framework/APDU;)V 7 {
			.stack 3;
			.locals 1;

			.descriptor	Ljavacard/framework/APDU;	0.10;

				L0:	aload_0;
					invokevirtual 16;		// selectingApplet()Z
					ifeq L2;
				L1:	return;
				L2:	aload_1;
					invokevirtual 5;		// getBuffer()[B
					astore_2;
					aload_2;
					sconst_1;
					baload;
					slookupswitch L4 1 6 L3;
				L3:	sconst_1;
					sconst_0;
					invokestatic 17;		// org/globalplatform/contactless/GPCLSystem.setCommunicationInterface(SZ)V
					aload_2;
					sconst_2;
					sconst_3;
					invokestatic 6;		// uicc/hci/framework/HCIDevice.isHCIServiceAvailable(S)B
					bastore;
					goto L5;
				L4:	sspush 27904;
					invokestatic 7;		// javacard/framework/ISOException.throwIt(S)V
				L5:	aload_1;
					sconst_2;
					sconst_1;
					invokevirtual 8;		// setOutgoingAndSend(SS)V
					return;
		}

		.method public onCallback(BLuicc/hci/framework/HCIMessage;)V 8 {
			.stack 0;
			.locals 0;

			.descriptor	Luicc/hci/framework/HCIMessage;	1.1;

				L0:	return;
		}

		.method public uninstall()V 9 {
			.stack 2;
			.locals 0;

				L0:	sconst_1;
					sconst_1;
					invokestatic 17;		// org/globalplatform/contactless/GPCLSystem.setCommunicationInterface(SZ)V
					return;
		}

	}

}
