// converted by version  [v3.0.2]
// on Fri May 24 11:14:44 CEST 2013

.package uicc/hci/test/framework/api_1_hsr_gen {
	.aid 0xA0:0x0:0x0:0x0:0x9:0x0:0x5:0xFF:0xFF:0xFF:0xFF:0x89:0x21:0x0:0x0:0x0;
	.version 1.0;

	.imports {
		0xA0:0x0:0x0:0x0:0x62:0x1:0x1 1.4;		//javacard/framework
		0xA0:0x0:0x0:0x0:0x9:0x0:0x5:0xFF:0xFF:0xFF:0xFF:0x89:0x16:0x1:0x0:0x0 1.0;		//uicc/hci/framework
		0xA0:0x0:0x0:0x0:0x9:0x0:0x5:0xFF:0xFF:0xFF:0xFF:0x89:0x16:0x2:0x1:0x0 1.0;		//uicc/hci/services/cardemulation
		0xA0:0x0:0x0:0x0:0x62:0x0:0x1 1.0;		//java/lang
		0xA0:0x0:0x0:0x0:0x9:0x0:0x5:0xFF:0xFF:0xFF:0xFF:0x89:0x16:0x2:0x2:0x0 1.0;		//uicc/hci/services/connectivity
		0xA0:0x0:0x0:0x0:0x9:0x0:0x5:0xFF:0xFF:0xFF:0xFF:0x89:0x16:0x2:0x3:0x0 1.0;		//uicc/hci/services/readermode
	}

	.applet {
		0xA0:0x0:0x0:0x0:0x9:0x0:0x5:0xFF:0xFF:0xFF:0xFF:0x89:0x21:0x9:0x1:0x2 Api_1_Hsr_Gen_1;
		0xA0:0x0:0x0:0x0:0x9:0x0:0x5:0xFF:0xFF:0xFF:0xFF:0x89:0x21:0x9:0x2:0x2 Api_1_Hsr_Gen_2;
		0xA0:0x0:0x0:0x0:0x9:0x0:0x5:0xFF:0xFF:0xFF:0xFF:0x89:0x21:0x9:0x3:0x2 Api_1_Hsr_Gen_3;
	}

	.constantPool {
		// 0
		instanceFieldRef 2.2 Api_1_Hsr_Gen_1/ceService;
		// 1
		instanceFieldRef 4.2 Api_1_Hsr_Gen_2/cnnService;
		// 2
		instanceFieldRef 5.2 Api_1_Hsr_Gen_3/rdrService;
		// 3
		staticMethodRef 1.4.0(S)Luicc/hci/framework/HCIService;;		// uicc/hci/framework/HCIDevice.getHCIService(S)Luicc/hci/framework/HCIService;
			.descriptor	Luicc/hci/framework/HCIService;	1.2;

		// 4
		.classRef 2.2;		// uicc/hci/services/cardemulation/CardEmulationService
		// 5
		staticMethodRef 0.3.0()V;		// javacard/framework/Applet.<init>()V
		// 6
		staticMethodRef 0.7.1(S)V;		// javacard/framework/ISOException.throwIt(S)V
		// 7
		.classRef Api_1_Hsr_Gen_1;
		// 8
		staticMethodRef Api_1_Hsr_Gen_1/<init>()V;
		// 9
		virtualMethodRef 0.3.3()Z;		// selectingApplet()Z
		// 10
		virtualMethodRef 0.10.1()[B;		// getBuffer()[B
		// 11
		virtualMethodRef 1.3.1()S;		// getReason()S
		// 12
		virtualMethodRef 0.3.1()V;		// register()V
		// 13
		.classRef 4.2;		// uicc/hci/services/connectivity/ConnectivityService
		// 14
		.classRef 1.3;		// uicc/hci/framework/HCIException
		// 15
		.classRef Api_1_Hsr_Gen_2;
		// 16
		staticMethodRef Api_1_Hsr_Gen_2/<init>()V;
		// 17
		virtualMethodRef 0.3.3()Z;		// selectingApplet()Z
		// 18
		virtualMethodRef 0.3.1()V;		// register()V
		// 19
		.classRef 5.2;		// uicc/hci/services/readermode/ReaderService
		// 20
		virtualMethodRef 0.3.1()V;		// register()V
		// 21
		.classRef Api_1_Hsr_Gen_3;
		// 22
		staticMethodRef Api_1_Hsr_Gen_3/<init>()V;
		// 23
		virtualMethodRef 0.3.3()Z;		// selectingApplet()Z
	}

	.class public Api_1_Hsr_Gen_1 0 extends 0.3 {		// extends javacard/framework/Applet

		.shareable;

		.fields {
			private 2.2 ceService 0;		// Luicc/hci/services/cardemulation/CardEmulationService;
			private static final short SW_EVENT_NOT_SUPPORTED = 28417;		// S
			private static final short SW_METHOD_NOT_SUPPORTED = 28418;		// S
			private static final byte INS_EVENT_TM_FAILED = 16;		// B
			private static final byte INS_EVENT_RCP_FAILED = 17;		// B
			private static final byte INS_EVENT_GET_PARAM = 18;		// B
			private static final byte INS_EVENT_SEND_DATA = 19;		// B
			private static final byte INS_EVENT_FIELD_OFF = 20;		// B
			private static final byte INS_WRONG_EVENT = 22;		// B
			private static final byte INS_EVENT_STATUS_CHANGED = 21;		// B
		}

		.publicMethodTable 7 {
			equals(Ljava/lang/Object;)Z;
			register()V;
			register([BSB)V;
			selectingApplet()Z;
			deselect()V;
			getShareableInterfaceObject(Ljavacard/framework/AID;B)Ljavacard/framework/Shareable;;
			select()Z;
			process(Ljavacard/framework/APDU;)V;
			onCallback(BLuicc/hci/framework/HCIMessage;)V;
		}

		.packageMethodTable 0 {
		}

		.implementedInterfaceInfoTable { 
			.interface 0.2 { 		// javacard/framework/Shareable
			}

			.interface 1.0 { 		// uicc/hci/framework/HCIListener
				8;		// onCallback(BLuicc/hci/framework/HCIMessage;)V
			}

			.interface 2.0 { 		// uicc/hci/services/cardemulation/CardEmulationListener
				8;		// onCallback(BLuicc/hci/framework/HCIMessage;)V
			}

		}

		.method private <init>()V {
			.stack 2;
			.locals 1;

				L0:	aload_0;
					invokespecial 5;		// javacard/framework/Applet.<init>()V
					aload_0;
					invokevirtual 20;		// register()V
				L1:	aload_0;
					sconst_3;
					invokestatic 3;		// uicc/hci/framework/HCIDevice.getHCIService(S)Luicc/hci/framework/HCIService;
					checkcast 0 4;		// T_CLASSORINTERFACE uicc/hci/services/cardemulation/CardEmulationService
					putfield_a 0;		// reference uicc/hci/test/framework/api_1_hsr_gen/Api_1_Hsr_Gen_1.ceService
					getfield_a_this 0;		// reference uicc/hci/test/framework/api_1_hsr_gen/Api_1_Hsr_Gen_1.ceService
					aload_0;
					invokeinterface 2 4 0;		// uicc/hci/services/cardemulation/CardEmulationService
				L2:	goto L4;
				L3:	astore_1;
					sspush 27012;
					invokestatic 6;		// javacard/framework/ISOException.throwIt(S)V
				L4:	return;
			.exceptionTable {
				// start_block end_block handler_block catch_type_index
				L1 L2 L3 14;
			}
		}

		.method public static install([BSB)V 0 {
			.stack 2;
			.locals 0;

				L0:	new 7;		// uicc/hci/test/framework/api_1_hsr_gen/Api_1_Hsr_Gen_1
					dup;
					invokespecial 8;		// uicc/hci/test/framework/api_1_hsr_gen/Api_1_Hsr_Gen_1.<init>()V
					pop;
					return;
		}

		.method public process(Ljavacard/framework/APDU;)V 7 {
			.stack 2;
			.locals 2;

			.descriptor	Ljavacard/framework/APDU;	0.10;

				L0:	aload_0;
					invokevirtual 9;		// selectingApplet()Z
					ifeq L2;
				L1:	return;
				L2:	aload_1;
					invokevirtual 10;		// getBuffer()[B
					astore_2;
					aload_2;
					sconst_1;
					baload;
					stableswitch L39 16 22 L3 L8 L13 L18 L23 L28 L34;
				L3:	getfield_a_this 0;		// reference uicc/hci/test/framework/api_1_hsr_gen/Api_1_Hsr_Gen_1.ceService
					bspush -127;
					invokeinterface 2 4 5;		// uicc/hci/services/cardemulation/CardEmulationService
					ifeq L5;
				L4:	sspush 28418;
					invokestatic 6;		// javacard/framework/ISOException.throwIt(S)V
				L5:	goto L7;
				L6:	astore_3;
					sspush 28417;
					invokestatic 6;		// javacard/framework/ISOException.throwIt(S)V
				L7:	return;
				L8:	getfield_a_this 0;		// reference uicc/hci/test/framework/api_1_hsr_gen/Api_1_Hsr_Gen_1.ceService
					bspush -126;
					invokeinterface 2 4 5;		// uicc/hci/services/cardemulation/CardEmulationService
					ifeq L10;
				L9:	sspush 28418;
					invokestatic 6;		// javacard/framework/ISOException.throwIt(S)V
				L10:	goto L12;
				L11:	astore_3;
					sspush 28417;
					invokestatic 6;		// javacard/framework/ISOException.throwIt(S)V
				L12:	return;
				L13:	getfield_a_this 0;		// reference uicc/hci/test/framework/api_1_hsr_gen/Api_1_Hsr_Gen_1.ceService
					sconst_1;
					invokeinterface 2 4 5;		// uicc/hci/services/cardemulation/CardEmulationService
					ifeq L15;
				L14:	sspush 28418;
					invokestatic 6;		// javacard/framework/ISOException.throwIt(S)V
				L15:	goto L17;
				L16:	astore_3;
					sspush 28417;
					invokestatic 6;		// javacard/framework/ISOException.throwIt(S)V
				L17:	return;
				L18:	getfield_a_this 0;		// reference uicc/hci/test/framework/api_1_hsr_gen/Api_1_Hsr_Gen_1.ceService
					bspush 80;
					invokeinterface 2 4 5;		// uicc/hci/services/cardemulation/CardEmulationService
					ifeq L20;
				L19:	sspush 28418;
					invokestatic 6;		// javacard/framework/ISOException.throwIt(S)V
				L20:	goto L22;
				L21:	astore_3;
					sspush 28417;
					invokestatic 6;		// javacard/framework/ISOException.throwIt(S)V
				L22:	return;
				L23:	getfield_a_this 0;		// reference uicc/hci/test/framework/api_1_hsr_gen/Api_1_Hsr_Gen_1.ceService
					bspush 84;
					invokeinterface 2 4 5;		// uicc/hci/services/cardemulation/CardEmulationService
					ifeq L25;
				L24:	sspush 28418;
					invokestatic 6;		// javacard/framework/ISOException.throwIt(S)V
				L25:	goto L27;
				L26:	astore_3;
					sspush 28417;
					invokestatic 6;		// javacard/framework/ISOException.throwIt(S)V
				L27:	return;
				L28:	getfield_a_this 0;		// reference uicc/hci/test/framework/api_1_hsr_gen/Api_1_Hsr_Gen_1.ceService
					bspush 80;
					invokeinterface 2 4 3;		// uicc/hci/services/cardemulation/CardEmulationService
				L29:	goto L31;
				L30:	astore_3;
					sspush 28417;
					invokestatic 6;		// javacard/framework/ISOException.throwIt(S)V
				L31:	getfield_a_this 0;		// reference uicc/hci/test/framework/api_1_hsr_gen/Api_1_Hsr_Gen_1.ceService
					bspush 80;
					invokeinterface 2 4 5;		// uicc/hci/services/cardemulation/CardEmulationService
					ifne L33;
				L32:	sspush 28418;
					invokestatic 6;		// javacard/framework/ISOException.throwIt(S)V
				L33:	return;
				L34:	getfield_a_this 0;		// reference uicc/hci/test/framework/api_1_hsr_gen/Api_1_Hsr_Gen_1.ceService
					sconst_2;
					invokeinterface 2 4 5;		// uicc/hci/services/cardemulation/CardEmulationService
					pop;
				L35:	goto L38;
				L36:	astore_3;
					aload_3;
					invokevirtual 11;		// getReason()S
					bspush 6;
					if_scmpne L38;
				L37:	return;
				L38:	sspush 28417;
					invokestatic 6;		// javacard/framework/ISOException.throwIt(S)V
				L39:	sspush 27904;
					invokestatic 6;		// javacard/framework/ISOException.throwIt(S)V
					return;
			.exceptionTable {
				// start_block end_block handler_block catch_type_index
				L3 L5 L6 14;
				L8 L10 L11 14;
				L13 L15 L16 14;
				L18 L20 L21 14;
				L23 L25 L26 14;
				L28 L29 L30 14;
				L34 L35 L36 14;
			}
		}

		.method public onCallback(BLuicc/hci/framework/HCIMessage;)V 8 {
			.stack 0;
			.locals 0;

			.descriptor	Luicc/hci/framework/HCIMessage;	1.1;

				L0:	return;
		}

	}

	.class public Api_1_Hsr_Gen_2 1 extends 0.3 {		// extends javacard/framework/Applet

		.shareable;

		.fields {
			private 4.2 cnnService 0;		// Luicc/hci/services/connectivity/ConnectivityService;
			private static final short SW_EVENT_NOT_SUPPORTED = 28417;		// S
			private static final short SW_METHOD_NOT_SUPPORTED = 28418;		// S
			private static final byte INS_EVENT_TM_FAILED = 16;		// B
			private static final byte INS_EVENT_RCP_FAILED = 17;		// B
			private static final byte INS_EVENT_STAND_BY = 18;		// B
			private static final byte INS_EVENT_STATUS_CHANGED = 21;		// B
			private static final byte INS_WRONG_EVENT = 22;		// B
		}

		.publicMethodTable 7 {
			equals(Ljava/lang/Object;)Z;
			register()V;
			register([BSB)V;
			selectingApplet()Z;
			deselect()V;
			getShareableInterfaceObject(Ljavacard/framework/AID;B)Ljavacard/framework/Shareable;;
			select()Z;
			process(Ljavacard/framework/APDU;)V;
			onCallback(BLuicc/hci/framework/HCIMessage;)V;
		}

		.packageMethodTable 0 {
		}

		.implementedInterfaceInfoTable { 
			.interface 0.2 { 		// javacard/framework/Shareable
			}

			.interface 1.0 { 		// uicc/hci/framework/HCIListener
				8;		// onCallback(BLuicc/hci/framework/HCIMessage;)V
			}

			.interface 4.0 { 		// uicc/hci/services/connectivity/ConnectivityListener
				8;		// onCallback(BLuicc/hci/framework/HCIMessage;)V
			}

		}

		.method private <init>()V {
			.stack 2;
			.locals 1;

				L0:	aload_0;
					invokespecial 5;		// javacard/framework/Applet.<init>()V
					aload_0;
					invokevirtual 12;		// register()V
				L1:	aload_0;
					sconst_4;
					invokestatic 3;		// uicc/hci/framework/HCIDevice.getHCIService(S)Luicc/hci/framework/HCIService;
					checkcast 0 13;		// T_CLASSORINTERFACE uicc/hci/services/connectivity/ConnectivityService
					putfield_a 1;		// reference uicc/hci/test/framework/api_1_hsr_gen/Api_1_Hsr_Gen_2.cnnService
					getfield_a_this 1;		// reference uicc/hci/test/framework/api_1_hsr_gen/Api_1_Hsr_Gen_2.cnnService
					aload_0;
					invokeinterface 2 13 0;		// uicc/hci/services/connectivity/ConnectivityService
				L2:	goto L4;
				L3:	astore_1;
					sspush 27012;
					invokestatic 6;		// javacard/framework/ISOException.throwIt(S)V
				L4:	return;
			.exceptionTable {
				// start_block end_block handler_block catch_type_index
				L1 L2 L3 14;
			}
		}

		.method public static install([BSB)V 0 {
			.stack 2;
			.locals 0;

				L0:	new 15;		// uicc/hci/test/framework/api_1_hsr_gen/Api_1_Hsr_Gen_2
					dup;
					invokespecial 16;		// uicc/hci/test/framework/api_1_hsr_gen/Api_1_Hsr_Gen_2.<init>()V
					pop;
					return;
		}

		.method public process(Ljavacard/framework/APDU;)V 7 {
			.stack 2;
			.locals 2;

			.descriptor	Ljavacard/framework/APDU;	0.10;

				L0:	aload_0;
					invokevirtual 17;		// selectingApplet()Z
					ifeq L2;
				L1:	return;
				L2:	aload_1;
					invokevirtual 10;		// getBuffer()[B
					astore_2;
					aload_2;
					sconst_1;
					baload;
					stableswitch L29 16 22 L3 L8 L13 L29 L29 L18 L24;
				L3:	getfield_a_this 1;		// reference uicc/hci/test/framework/api_1_hsr_gen/Api_1_Hsr_Gen_2.cnnService
					bspush -127;
					invokeinterface 2 13 5;		// uicc/hci/services/connectivity/ConnectivityService
					ifeq L5;
				L4:	sspush 28418;
					invokestatic 6;		// javacard/framework/ISOException.throwIt(S)V
				L5:	goto L7;
				L6:	astore_3;
					sspush 28417;
					invokestatic 6;		// javacard/framework/ISOException.throwIt(S)V
				L7:	return;
				L8:	getfield_a_this 1;		// reference uicc/hci/test/framework/api_1_hsr_gen/Api_1_Hsr_Gen_2.cnnService
					bspush -126;
					invokeinterface 2 13 5;		// uicc/hci/services/connectivity/ConnectivityService
					ifeq L10;
				L9:	sspush 28418;
					invokestatic 6;		// javacard/framework/ISOException.throwIt(S)V
				L10:	goto L12;
				L11:	astore_3;
					sspush 28417;
					invokestatic 6;		// javacard/framework/ISOException.throwIt(S)V
				L12:	return;
				L13:	getfield_a_this 1;		// reference uicc/hci/test/framework/api_1_hsr_gen/Api_1_Hsr_Gen_2.cnnService
					bspush 80;
					invokeinterface 2 13 5;		// uicc/hci/services/connectivity/ConnectivityService
					ifeq L15;
				L14:	sspush 28418;
					invokestatic 6;		// javacard/framework/ISOException.throwIt(S)V
				L15:	goto L17;
				L16:	astore_3;
					sspush 28417;
					invokestatic 6;		// javacard/framework/ISOException.throwIt(S)V
				L17:	return;
				L18:	getfield_a_this 1;		// reference uicc/hci/test/framework/api_1_hsr_gen/Api_1_Hsr_Gen_2.cnnService
					bspush 80;
					invokeinterface 2 13 3;		// uicc/hci/services/connectivity/ConnectivityService
				L19:	goto L21;
				L20:	astore_3;
					sspush 28417;
					invokestatic 6;		// javacard/framework/ISOException.throwIt(S)V
				L21:	getfield_a_this 1;		// reference uicc/hci/test/framework/api_1_hsr_gen/Api_1_Hsr_Gen_2.cnnService
					bspush 80;
					invokeinterface 2 13 5;		// uicc/hci/services/connectivity/ConnectivityService
					ifne L23;
				L22:	sspush 28418;
					invokestatic 6;		// javacard/framework/ISOException.throwIt(S)V
				L23:	return;
				L24:	getfield_a_this 1;		// reference uicc/hci/test/framework/api_1_hsr_gen/Api_1_Hsr_Gen_2.cnnService
					sconst_2;
					invokeinterface 2 13 5;		// uicc/hci/services/connectivity/ConnectivityService
					pop;
				L25:	goto L28;
				L26:	astore_3;
					aload_3;
					invokevirtual 11;		// getReason()S
					bspush 6;
					if_scmpne L28;
				L27:	return;
				L28:	sspush 28417;
					invokestatic 6;		// javacard/framework/ISOException.throwIt(S)V
				L29:	sspush 27904;
					invokestatic 6;		// javacard/framework/ISOException.throwIt(S)V
					return;
			.exceptionTable {
				// start_block end_block handler_block catch_type_index
				L3 L5 L6 14;
				L8 L10 L11 14;
				L13 L15 L16 14;
				L18 L19 L20 14;
				L24 L25 L26 14;
			}
		}

		.method public onCallback(BLuicc/hci/framework/HCIMessage;)V 8 {
			.stack 0;
			.locals 0;

			.descriptor	Luicc/hci/framework/HCIMessage;	1.1;

				L0:	return;
		}

	}

	.class public Api_1_Hsr_Gen_3 2 extends 0.3 {		// extends javacard/framework/Applet

		.shareable;

		.fields {
			private 5.2 rdrService 0;		// Luicc/hci/services/readermode/ReaderService;
			private static final short SW_EVENT_NOT_SUPPORTED = 28417;		// S
			private static final short SW_METHOD_NOT_SUPPORTED = 28418;		// S
			private static final byte INS_EVENT_T_WRT_EXCH_DATA = 33;		// B
			private static final byte INS_EVENT_T_TARG_DISC = 34;		// B
			private static final byte INS_EVENT_T_PARAM_RESP = 35;		// B
			private static final byte INS_EVENT_T_RCP_FAILED = 36;		// B
			private static final byte INS_EVENT_T_TM_FAILED = 37;		// B
			private static final byte INS_EVENT_F_TM_FAILED = 16;		// B
			private static final byte INS_EVENT_F_PARAM_RESP = 17;		// B
			private static final byte INS_EVENT_F_WRT_EXCH_DATA = 18;		// B
			private static final byte INS_EVENT_F_TARG_DISC = 19;		// B
			private static final byte INS_EVENT_F_RCP_FAILED = 20;		// B
			private static final byte INS_WRONG_EVENT = 23;		// B
		}

		.publicMethodTable 7 {
			equals(Ljava/lang/Object;)Z;
			register()V;
			register([BSB)V;
			selectingApplet()Z;
			deselect()V;
			getShareableInterfaceObject(Ljavacard/framework/AID;B)Ljavacard/framework/Shareable;;
			select()Z;
			process(Ljavacard/framework/APDU;)V;
			onCallback(BLuicc/hci/framework/HCIMessage;)V;
		}

		.packageMethodTable 0 {
		}

		.implementedInterfaceInfoTable { 
			.interface 0.2 { 		// javacard/framework/Shareable
			}

			.interface 1.0 { 		// uicc/hci/framework/HCIListener
				8;		// onCallback(BLuicc/hci/framework/HCIMessage;)V
			}

			.interface 5.0 { 		// uicc/hci/services/readermode/ReaderListener
				8;		// onCallback(BLuicc/hci/framework/HCIMessage;)V
			}

		}

		.method private <init>()V {
			.stack 2;
			.locals 1;

				L0:	aload_0;
					invokespecial 5;		// javacard/framework/Applet.<init>()V
					aload_0;
					invokevirtual 18;		// register()V
				L1:	aload_0;
					sconst_2;
					invokestatic 3;		// uicc/hci/framework/HCIDevice.getHCIService(S)Luicc/hci/framework/HCIService;
					checkcast 0 19;		// T_CLASSORINTERFACE uicc/hci/services/readermode/ReaderService
					putfield_a 2;		// reference uicc/hci/test/framework/api_1_hsr_gen/Api_1_Hsr_Gen_3.rdrService
					getfield_a_this 2;		// reference uicc/hci/test/framework/api_1_hsr_gen/Api_1_Hsr_Gen_3.rdrService
					aload_0;
					invokeinterface 2 19 0;		// uicc/hci/services/readermode/ReaderService
				L2:	goto L4;
				L3:	astore_1;
					sspush 27012;
					invokestatic 6;		// javacard/framework/ISOException.throwIt(S)V
				L4:	return;
			.exceptionTable {
				// start_block end_block handler_block catch_type_index
				L1 L2 L3 14;
			}
		}

		.method public static install([BSB)V 0 {
			.stack 2;
			.locals 0;

				L0:	new 21;		// uicc/hci/test/framework/api_1_hsr_gen/Api_1_Hsr_Gen_3
					dup;
					invokespecial 22;		// uicc/hci/test/framework/api_1_hsr_gen/Api_1_Hsr_Gen_3.<init>()V
					pop;
					return;
		}

		.method public process(Ljavacard/framework/APDU;)V 7 {
			.stack 2;
			.locals 2;

			.descriptor	Ljavacard/framework/APDU;	0.10;

				L0:	aload_0;
					invokevirtual 23;		// selectingApplet()Z
					ifeq L2;
				L1:	return;
				L2:	aload_1;
					invokevirtual 10;		// getBuffer()[B
					astore_2;
					aload_2;
					sconst_1;
					baload;
					stableswitch L68 16 37 L33 L57 L45 L51 L39 L68 L68 L63 L68 L68 L68 L68 L68 L68 L68 L68 L68 L15 L21 L27 L9 L3;
				L3:	getfield_a_this 2;		// reference uicc/hci/test/framework/api_1_hsr_gen/Api_1_Hsr_Gen_3.rdrService
					bspush -127;
					invokeinterface 2 19 3;		// uicc/hci/services/readermode/ReaderService
				L4:	goto L6;
				L5:	astore_3;
					sspush 28417;
					invokestatic 6;		// javacard/framework/ISOException.throwIt(S)V
				L6:	getfield_a_this 2;		// reference uicc/hci/test/framework/api_1_hsr_gen/Api_1_Hsr_Gen_3.rdrService
					bspush -127;
					invokeinterface 2 19 5;		// uicc/hci/services/readermode/ReaderService
					ifne L8;
				L7:	sspush 28418;
					invokestatic 6;		// javacard/framework/ISOException.throwIt(S)V
				L8:	return;
				L9:	getfield_a_this 2;		// reference uicc/hci/test/framework/api_1_hsr_gen/Api_1_Hsr_Gen_3.rdrService
					bspush -126;
					invokeinterface 2 19 3;		// uicc/hci/services/readermode/ReaderService
				L10:	goto L12;
				L11:	astore_3;
					sspush 28417;
					invokestatic 6;		// javacard/framework/ISOException.throwIt(S)V
				L12:	getfield_a_this 2;		// reference uicc/hci/test/framework/api_1_hsr_gen/Api_1_Hsr_Gen_3.rdrService
					bspush -126;
					invokeinterface 2 19 5;		// uicc/hci/services/readermode/ReaderService
					ifne L14;
				L13:	sspush 28418;
					invokestatic 6;		// javacard/framework/ISOException.throwIt(S)V
				L14:	return;
				L15:	getfield_a_this 2;		// reference uicc/hci/test/framework/api_1_hsr_gen/Api_1_Hsr_Gen_3.rdrService
					sconst_2;
					invokeinterface 2 19 3;		// uicc/hci/services/readermode/ReaderService
				L16:	goto L18;
				L17:	astore_3;
					sspush 28417;
					invokestatic 6;		// javacard/framework/ISOException.throwIt(S)V
				L18:	getfield_a_this 2;		// reference uicc/hci/test/framework/api_1_hsr_gen/Api_1_Hsr_Gen_3.rdrService
					sconst_2;
					invokeinterface 2 19 5;		// uicc/hci/services/readermode/ReaderService
					ifne L20;
				L19:	sspush 28418;
					invokestatic 6;		// javacard/framework/ISOException.throwIt(S)V
				L20:	return;
				L21:	getfield_a_this 2;		// reference uicc/hci/test/framework/api_1_hsr_gen/Api_1_Hsr_Gen_3.rdrService
					bspush 80;
					invokeinterface 2 19 3;		// uicc/hci/services/readermode/ReaderService
				L22:	goto L24;
				L23:	astore_3;
					sspush 28417;
					invokestatic 6;		// javacard/framework/ISOException.throwIt(S)V
				L24:	getfield_a_this 2;		// reference uicc/hci/test/framework/api_1_hsr_gen/Api_1_Hsr_Gen_3.rdrService
					bspush 80;
					invokeinterface 2 19 5;		// uicc/hci/services/readermode/ReaderService
					ifne L26;
				L25:	sspush 28418;
					invokestatic 6;		// javacard/framework/ISOException.throwIt(S)V
				L26:	return;
				L27:	getfield_a_this 2;		// reference uicc/hci/test/framework/api_1_hsr_gen/Api_1_Hsr_Gen_3.rdrService
					sconst_1;
					invokeinterface 2 19 3;		// uicc/hci/services/readermode/ReaderService
				L28:	goto L30;
				L29:	astore_3;
					sspush 28417;
					invokestatic 6;		// javacard/framework/ISOException.throwIt(S)V
				L30:	getfield_a_this 2;		// reference uicc/hci/test/framework/api_1_hsr_gen/Api_1_Hsr_Gen_3.rdrService
					sconst_1;
					invokeinterface 2 19 5;		// uicc/hci/services/readermode/ReaderService
					ifne L32;
				L31:	sspush 28418;
					invokestatic 6;		// javacard/framework/ISOException.throwIt(S)V
				L32:	return;
				L33:	getfield_a_this 2;		// reference uicc/hci/test/framework/api_1_hsr_gen/Api_1_Hsr_Gen_3.rdrService
					bspush -127;
					invokeinterface 2 19 3;		// uicc/hci/services/readermode/ReaderService
					getfield_a_this 2;		// reference uicc/hci/test/framework/api_1_hsr_gen/Api_1_Hsr_Gen_3.rdrService
					bspush -127;
					invokeinterface 2 19 4;		// uicc/hci/services/readermode/ReaderService
				L34:	goto L36;
				L35:	astore_3;
					sspush 28417;
					invokestatic 6;		// javacard/framework/ISOException.throwIt(S)V
				L36:	getfield_a_this 2;		// reference uicc/hci/test/framework/api_1_hsr_gen/Api_1_Hsr_Gen_3.rdrService
					bspush -127;
					invokeinterface 2 19 5;		// uicc/hci/services/readermode/ReaderService
					ifeq L38;
				L37:	sspush 28418;
					invokestatic 6;		// javacard/framework/ISOException.throwIt(S)V
				L38:	return;
				L39:	getfield_a_this 2;		// reference uicc/hci/test/framework/api_1_hsr_gen/Api_1_Hsr_Gen_3.rdrService
					bspush -126;
					invokeinterface 2 19 3;		// uicc/hci/services/readermode/ReaderService
					getfield_a_this 2;		// reference uicc/hci/test/framework/api_1_hsr_gen/Api_1_Hsr_Gen_3.rdrService
					bspush -126;
					invokeinterface 2 19 4;		// uicc/hci/services/readermode/ReaderService
				L40:	goto L42;
				L41:	astore_3;
					sspush 28417;
					invokestatic 6;		// javacard/framework/ISOException.throwIt(S)V
				L42:	getfield_a_this 2;		// reference uicc/hci/test/framework/api_1_hsr_gen/Api_1_Hsr_Gen_3.rdrService
					bspush -126;
					invokeinterface 2 19 5;		// uicc/hci/services/readermode/ReaderService
					ifeq L44;
				L43:	sspush 28418;
					invokestatic 6;		// javacard/framework/ISOException.throwIt(S)V
				L44:	return;
				L45:	getfield_a_this 2;		// reference uicc/hci/test/framework/api_1_hsr_gen/Api_1_Hsr_Gen_3.rdrService
					sconst_2;
					invokeinterface 2 19 3;		// uicc/hci/services/readermode/ReaderService
					getfield_a_this 2;		// reference uicc/hci/test/framework/api_1_hsr_gen/Api_1_Hsr_Gen_3.rdrService
					sconst_2;
					invokeinterface 2 19 4;		// uicc/hci/services/readermode/ReaderService
				L46:	goto L48;
				L47:	astore_3;
					sspush 28417;
					invokestatic 6;		// javacard/framework/ISOException.throwIt(S)V
				L48:	getfield_a_this 2;		// reference uicc/hci/test/framework/api_1_hsr_gen/Api_1_Hsr_Gen_3.rdrService
					sconst_2;
					invokeinterface 2 19 5;		// uicc/hci/services/readermode/ReaderService
					ifeq L50;
				L49:	sspush 28418;
					invokestatic 6;		// javacard/framework/ISOException.throwIt(S)V
				L50:	return;
				L51:	getfield_a_this 2;		// reference uicc/hci/test/framework/api_1_hsr_gen/Api_1_Hsr_Gen_3.rdrService
					bspush 80;
					invokeinterface 2 19 3;		// uicc/hci/services/readermode/ReaderService
					getfield_a_this 2;		// reference uicc/hci/test/framework/api_1_hsr_gen/Api_1_Hsr_Gen_3.rdrService
					bspush 80;
					invokeinterface 2 19 4;		// uicc/hci/services/readermode/ReaderService
				L52:	goto L54;
				L53:	astore_3;
					sspush 28417;
					invokestatic 6;		// javacard/framework/ISOException.throwIt(S)V
				L54:	getfield_a_this 2;		// reference uicc/hci/test/framework/api_1_hsr_gen/Api_1_Hsr_Gen_3.rdrService
					bspush 80;
					invokeinterface 2 19 5;		// uicc/hci/services/readermode/ReaderService
					ifeq L56;
				L55:	sspush 28418;
					invokestatic 6;		// javacard/framework/ISOException.throwIt(S)V
				L56:	return;
				L57:	getfield_a_this 2;		// reference uicc/hci/test/framework/api_1_hsr_gen/Api_1_Hsr_Gen_3.rdrService
					sconst_1;
					invokeinterface 2 19 3;		// uicc/hci/services/readermode/ReaderService
					getfield_a_this 2;		// reference uicc/hci/test/framework/api_1_hsr_gen/Api_1_Hsr_Gen_3.rdrService
					sconst_1;
					invokeinterface 2 19 4;		// uicc/hci/services/readermode/ReaderService
				L58:	goto L60;
				L59:	astore_3;
					sspush 28417;
					invokestatic 6;		// javacard/framework/ISOException.throwIt(S)V
				L60:	getfield_a_this 2;		// reference uicc/hci/test/framework/api_1_hsr_gen/Api_1_Hsr_Gen_3.rdrService
					sconst_1;
					invokeinterface 2 19 5;		// uicc/hci/services/readermode/ReaderService
					ifeq L62;
				L61:	sspush 28418;
					invokestatic 6;		// javacard/framework/ISOException.throwIt(S)V
				L62:	return;
				L63:	getfield_a_this 2;		// reference uicc/hci/test/framework/api_1_hsr_gen/Api_1_Hsr_Gen_3.rdrService
					bspush -124;
					invokeinterface 2 19 5;		// uicc/hci/services/readermode/ReaderService
					pop;
				L64:	goto L67;
				L65:	astore_3;
					aload_3;
					invokevirtual 11;		// getReason()S
					bspush 6;
					if_scmpne L67;
				L66:	return;
				L67:	sspush 28417;
					invokestatic 6;		// javacard/framework/ISOException.throwIt(S)V
				L68:	sspush 27904;
					invokestatic 6;		// javacard/framework/ISOException.throwIt(S)V
					return;
			.exceptionTable {
				// start_block end_block handler_block catch_type_index
				L3 L4 L5 14;
				L9 L10 L11 14;
				L15 L16 L17 14;
				L21 L22 L23 14;
				L27 L28 L29 14;
				L33 L34 L35 14;
				L39 L40 L41 14;
				L45 L46 L47 14;
				L51 L52 L53 14;
				L57 L58 L59 14;
				L63 L64 L65 14;
			}
		}

		.method public onCallback(BLuicc/hci/framework/HCIMessage;)V 8 {
			.stack 0;
			.locals 0;

			.descriptor	Luicc/hci/framework/HCIMessage;	1.1;

				L0:	return;
		}

	}

}
