// converted by version  [v3.0.2]
// on Fri Nov 08 11:49:03 CET 2013

.package uicc/hci/test/framework/api_1_hme_mty {
	.aid 0xA0:0x0:0x0:0x0:0x9:0x0:0x5:0xFF:0xFF:0xFF:0xFF:0x89:0x21:0x0:0x0:0x0;
	.version 1.0;

	.imports {
		0xA0:0x0:0x0:0x0:0x62:0x1:0x1 1.4;		//javacard/framework
		0xA0:0x0:0x0:0x0:0x9:0x0:0x5:0xFF:0xFF:0xFF:0xFF:0x89:0x16:0x1:0x0:0x0 1.0;		//uicc/hci/framework
		0xA0:0x0:0x0:0x0:0x9:0x0:0x5:0xFF:0xFF:0xFF:0xFF:0x89:0x16:0x2:0x1:0x0 1.0;		//uicc/hci/services/cardemulation
		0xA0:0x0:0x0:0x0:0x62:0x0:0x1 1.0;		//java/lang
		0xA0:0x0:0x0:0x0:0x9:0x0:0x5:0xFF:0xFF:0xFF:0xFF:0x89:0x16:0x2:0x2:0x0 1.0;		//uicc/hci/services/connectivity
	}

	.applet {
		0xA0:0x0:0x0:0x0:0x9:0x0:0x5:0xFF:0xFF:0xFF:0xFF:0x89:0x21:0xC:0x1:0x2 Api_1_Hme_Mty_1;
		0xA0:0x0:0x0:0x0:0x9:0x0:0x5:0xFF:0xFF:0xFF:0xFF:0x89:0x21:0xC:0x2:0x2 Api_1_Hme_Mty_2;
	}

	.constantPool {
		// 0
		instanceFieldRef 2.2 Api_1_Hme_Mty_1/ceService;
		// 1
		instanceFieldRef byte[] Api_1_Hme_Mty_1/exceptions;
		// 2
		instanceFieldRef byte Api_1_Hme_Mty_1/sentOnce;
		// 3
		instanceFieldRef boolean Api_1_Hme_Mty_1/isSet;
		// 4
		instanceFieldRef 4.2 Api_1_Hme_Mty_2/cnnService;
		// 5
		instanceFieldRef byte[] Api_1_Hme_Mty_2/exceptions;
		// 6
		staticMethodRef 0.7.1(S)V;		// javacard/framework/ISOException.throwIt(S)V
		// 7
		.classRef 1.3;		// uicc/hci/framework/HCIException
		// 8
		virtualMethodRef 0.3.1()V;		// register()V
		// 9
		staticMethodRef 1.4.0(S)Luicc/hci/framework/HCIService;;		// uicc/hci/framework/HCIDevice.getHCIService(S)Luicc/hci/framework/HCIService;
			.descriptor	Luicc/hci/framework/HCIService;	1.2;

		// 10
		.classRef Api_1_Hme_Mty_1;
		// 11
		staticMethodRef Api_1_Hme_Mty_1/<init>()V;
		// 12
		.classRef 2.1;		// uicc/hci/services/cardemulation/CardEmulationMessage
		// 13
		virtualMethodRef 0.3.1()V;		// register()V
		// 14
		.classRef 4.2;		// uicc/hci/services/connectivity/ConnectivityService
		// 15
		.classRef 2.2;		// uicc/hci/services/cardemulation/CardEmulationService
		// 16
		staticMethodRef 0.3.0()V;		// javacard/framework/Applet.<init>()V
		// 17
		.classRef Api_1_Hme_Mty_2;
		// 18
		staticMethodRef Api_1_Hme_Mty_2/<init>()V;
		// 19
		.classRef 1.1;		// uicc/hci/framework/HCIMessage
		// 20
		virtualMethodRef 0.3.3()Z;		// selectingApplet()Z
		// 21
		virtualMethodRef 0.10.1()[B;		// getBuffer()[B
	}

	.class public Api_1_Hme_Mty_1 0 extends 0.3 {		// extends javacard/framework/Applet

		.shareable;

		.fields {
			private 2.2 ceService 0;		// Luicc/hci/services/cardemulation/CardEmulationService;
			private byte[] exceptions 1;		// [B
			private byte sentOnce 2;		// B
			private boolean isSet 3;		// Z
		}

		.publicMethodTable 7 {
			equals(Ljava/lang/Object;)Z;
			register()V;
			register([BSB)V;
			selectingApplet()Z;
			deselect()V;
			getShareableInterfaceObject(Ljavacard/framework/AID;B)Ljavacard/framework/Shareable;;
			select()Z;
			process(Ljavacard/framework/APDU;)V;
			onCallback(BLuicc/hci/framework/HCIMessage;)V;
		}

		.packageMethodTable 0 {
		}

		.implementedInterfaceInfoTable { 
			.interface 0.2 { 		// javacard/framework/Shareable
			}

			.interface 1.0 { 		// uicc/hci/framework/HCIListener
				8;		// onCallback(BLuicc/hci/framework/HCIMessage;)V
			}

			.interface 2.0 { 		// uicc/hci/services/cardemulation/CardEmulationListener
				8;		// onCallback(BLuicc/hci/framework/HCIMessage;)V
			}

		}

		.method private <init>()V {
			.stack 2;
			.locals 1;

				L0:	aload_0;
					invokespecial 16;		// javacard/framework/Applet.<init>()V
					aload_0;
					invokevirtual 8;		// register()V
				L1:	aload_0;
					sconst_3;
					invokestatic 9;		// uicc/hci/framework/HCIDevice.getHCIService(S)Luicc/hci/framework/HCIService;
					checkcast 0 15;		// T_CLASSORINTERFACE uicc/hci/services/cardemulation/CardEmulationService
					putfield_a 0;		// reference uicc/hci/test/framework/api_1_hme_mty/Api_1_Hme_Mty_1.ceService
					getfield_a_this 0;		// reference uicc/hci/test/framework/api_1_hme_mty/Api_1_Hme_Mty_1.ceService
					aload_0;
					invokeinterface 2 15 0;		// uicc/hci/services/cardemulation/CardEmulationService
					getfield_a_this 0;		// reference uicc/hci/test/framework/api_1_hme_mty/Api_1_Hme_Mty_1.ceService
					bspush 80;
					invokeinterface 2 15 3;		// uicc/hci/services/cardemulation/CardEmulationService
				L2:	goto L4;
				L3:	astore_1;
					sspush 27012;
					invokestatic 6;		// javacard/framework/ISOException.throwIt(S)V
				L4:	aload_0;
					bspush 10;
					newarray 11;
					putfield_a 1;		// reference uicc/hci/test/framework/api_1_hme_mty/Api_1_Hme_Mty_1.exceptions
					aload_0;
					sconst_0;
					putfield_b 2;		// byte uicc/hci/test/framework/api_1_hme_mty/Api_1_Hme_Mty_1.sentOnce
					aload_0;
					sconst_0;
					putfield_b 3;		// boolean uicc/hci/test/framework/api_1_hme_mty/Api_1_Hme_Mty_1.isSet
					return;
			.exceptionTable {
				// start_block end_block handler_block catch_type_index
				L1 L2 L3 7;
			}
		}

		.method public static install([BSB)V 0 {
			.stack 2;
			.locals 0;

				L0:	new 10;		// uicc/hci/test/framework/api_1_hme_mty/Api_1_Hme_Mty_1
					dup;
					invokespecial 11;		// uicc/hci/test/framework/api_1_hme_mty/Api_1_Hme_Mty_1.<init>()V
					pop;
					return;
		}

		.method public onCallback(BLuicc/hci/framework/HCIMessage;)V 8 {
			.stack 4;
			.locals 1;

			.descriptor	Luicc/hci/framework/HCIMessage;	1.1;

				L0:	aload_2;
					checkcast 0 12;		// T_CLASSORINTERFACE uicc/hci/services/cardemulation/CardEmulationMessage
					astore_3;
					getfield_a_this 1;		// reference uicc/hci/test/framework/api_1_hme_mty/Api_1_Hme_Mty_1.exceptions
					bspush 8;
					bspush -112;
					bastore;
					getfield_a_this 1;		// reference uicc/hci/test/framework/api_1_hme_mty/Api_1_Hme_Mty_1.exceptions
					bspush 9;
					sconst_0;
					bastore;
					sload_1;
					slookupswitch L6 1 80 L1;
				L1:	getfield_b_this 2;		// byte uicc/hci/test/framework/api_1_hme_mty/Api_1_Hme_Mty_1.sentOnce
					ifne L3;
				L2:	aload_0;
					sconst_1;
					putfield_b 2;		// byte uicc/hci/test/framework/api_1_hme_mty/Api_1_Hme_Mty_1.sentOnce
					aload_3;
					getfield_a_this 1;		// reference uicc/hci/test/framework/api_1_hme_mty/Api_1_Hme_Mty_1.exceptions
					bspush 8;
					sconst_2;
					invokeinterface 4 12 8;		// uicc/hci/services/cardemulation/CardEmulationMessage
					return;
				L3:	getfield_b_this 3;		// boolean uicc/hci/test/framework/api_1_hme_mty/Api_1_Hme_Mty_1.isSet
					ifne L5;
				L4:	getfield_a_this 1;		// reference uicc/hci/test/framework/api_1_hme_mty/Api_1_Hme_Mty_1.exceptions
					sconst_2;
					aload_3;
					invokeinterface 1 12 2;		// uicc/hci/services/cardemulation/CardEmulationMessage
					bastore;
					aload_0;
					sconst_1;
					putfield_b 3;		// boolean uicc/hci/test/framework/api_1_hme_mty/Api_1_Hme_Mty_1.isSet
				L5:	aload_3;
					getfield_a_this 1;		// reference uicc/hci/test/framework/api_1_hme_mty/Api_1_Hme_Mty_1.exceptions
					sconst_0;
					bspush 10;
					invokeinterface 4 12 8;		// uicc/hci/services/cardemulation/CardEmulationMessage
				L6:	return;
		}

		.method public process(Ljavacard/framework/APDU;)V 7 {
			.stack 0;
			.locals 0;

			.descriptor	Ljavacard/framework/APDU;	0.10;

				L0:	return;
		}

	}

	.class public Api_1_Hme_Mty_2 1 extends 0.3 {		// extends javacard/framework/Applet

		.shareable;

		.fields {
			private 4.2 cnnService 0;		// Luicc/hci/services/connectivity/ConnectivityService;
			private byte[] exceptions 1;		// [B
			private static final short SW_EVENT_NOT_TRIGGERED = 28417;		// S
			private static final byte INS_CHECK_VB = 1;		// B
		}

		.publicMethodTable 7 {
			equals(Ljava/lang/Object;)Z;
			register()V;
			register([BSB)V;
			selectingApplet()Z;
			deselect()V;
			getShareableInterfaceObject(Ljavacard/framework/AID;B)Ljavacard/framework/Shareable;;
			select()Z;
			process(Ljavacard/framework/APDU;)V;
			onCallback(BLuicc/hci/framework/HCIMessage;)V;
		}

		.packageMethodTable 0 {
		}

		.implementedInterfaceInfoTable { 
			.interface 0.2 { 		// javacard/framework/Shareable
			}

			.interface 1.0 { 		// uicc/hci/framework/HCIListener
				8;		// onCallback(BLuicc/hci/framework/HCIMessage;)V
			}

			.interface 4.0 { 		// uicc/hci/services/connectivity/ConnectivityListener
				8;		// onCallback(BLuicc/hci/framework/HCIMessage;)V
			}

		}

		.method private <init>()V {
			.stack 2;
			.locals 1;

				L0:	aload_0;
					invokespecial 16;		// javacard/framework/Applet.<init>()V
					aload_0;
					invokevirtual 13;		// register()V
				L1:	aload_0;
					sconst_4;
					invokestatic 9;		// uicc/hci/framework/HCIDevice.getHCIService(S)Luicc/hci/framework/HCIService;
					checkcast 0 14;		// T_CLASSORINTERFACE uicc/hci/services/connectivity/ConnectivityService
					putfield_a 4;		// reference uicc/hci/test/framework/api_1_hme_mty/Api_1_Hme_Mty_2.cnnService
					getfield_a_this 4;		// reference uicc/hci/test/framework/api_1_hme_mty/Api_1_Hme_Mty_2.cnnService
					aload_0;
					invokeinterface 2 14 0;		// uicc/hci/services/connectivity/ConnectivityService
					getfield_a_this 4;		// reference uicc/hci/test/framework/api_1_hme_mty/Api_1_Hme_Mty_2.cnnService
					bspush 80;
					invokeinterface 2 14 3;		// uicc/hci/services/connectivity/ConnectivityService
				L2:	goto L4;
				L3:	astore_1;
					sspush 27012;
					invokestatic 6;		// javacard/framework/ISOException.throwIt(S)V
				L4:	aload_0;
					bspush 8;
					newarray 11;
					putfield_a 5;		// reference uicc/hci/test/framework/api_1_hme_mty/Api_1_Hme_Mty_2.exceptions
					return;
			.exceptionTable {
				// start_block end_block handler_block catch_type_index
				L1 L2 L3 7;
			}
		}

		.method public static install([BSB)V 0 {
			.stack 2;
			.locals 0;

				L0:	new 17;		// uicc/hci/test/framework/api_1_hme_mty/Api_1_Hme_Mty_2
					dup;
					invokespecial 18;		// uicc/hci/test/framework/api_1_hme_mty/Api_1_Hme_Mty_2.<init>()V
					pop;
					return;
		}

		.method public onCallback(BLuicc/hci/framework/HCIMessage;)V 8 {
			.stack 3;
			.locals 0;

			.descriptor	Luicc/hci/framework/HCIMessage;	1.1;

				L0:	sload_1;
					slookupswitch L2 1 80 L1;
				L1:	getfield_a_this 5;		// reference uicc/hci/test/framework/api_1_hme_mty/Api_1_Hme_Mty_2.exceptions
					sconst_2;
					aload_2;
					invokeinterface 1 19 2;		// uicc/hci/framework/HCIMessage
					bastore;
				L2:	return;
		}

		.method public process(Ljavacard/framework/APDU;)V 7 {
			.stack 2;
			.locals 1;

			.descriptor	Ljavacard/framework/APDU;	0.10;

				L0:	aload_0;
					invokevirtual 20;		// selectingApplet()Z
					ifeq L2;
				L1:	return;
				L2:	aload_1;
					invokevirtual 21;		// getBuffer()[B
					astore_2;
					aload_2;
					sconst_1;
					baload;
					slookupswitch L6 1 1 L3;
				L3:	getfield_a_this 5;		// reference uicc/hci/test/framework/api_1_hme_mty/Api_1_Hme_Mty_2.exceptions
					sconst_2;
					baload;
					sspush 255;
					sand;
					bspush 64;
					if_scmpeq L5;
				L4:	sspush 28417;
					invokestatic 6;		// javacard/framework/ISOException.throwIt(S)V
				L5:	return;
				L6:	sspush 27904;
					invokestatic 6;		// javacard/framework/ISOException.throwIt(S)V
					return;
		}

	}

}
