// converted by version  [v3.0.2]
// on Fri May 24 11:14:44 CEST 2013

.package uicc/hci/test/framework/api_1_hxp_trw {
	.aid 0xA0:0x0:0x0:0x0:0x9:0x0:0x5:0xFF:0xFF:0xFF:0xFF:0x89:0x21:0x0:0x0:0x0;
	.version 1.0;

	.imports {
		0xA0:0x0:0x0:0x0:0x62:0x1:0x1 1.4;		//javacard/framework
		0xA0:0x0:0x0:0x0:0x9:0x0:0x5:0xFF:0xFF:0xFF:0xFF:0x89:0x16:0x1:0x0:0x0 1.0;		//uicc/hci/framework
		0xA0:0x0:0x0:0x0:0x62:0x0:0x1 1.0;		//java/lang
	}

	.applet {
		0xA0:0x0:0x0:0x0:0x9:0x0:0x5:0xFF:0xFF:0xFF:0xFF:0x89:0x21:0x12:0x1:0x2 Api_1_Hxp_Trw_1;
	}

	.constantPool {
		// 0
		staticMethodRef 0.3.0()V;		// javacard/framework/Applet.<init>()V
		// 1
		virtualMethodRef 0.3.1()V;		// register()V
		// 2
		.classRef Api_1_Hxp_Trw_1;
		// 3
		staticMethodRef Api_1_Hxp_Trw_1/<init>()V;
		// 4
		.classRef 1.3;		// uicc/hci/framework/HCIException
		// 5
		virtualMethodRef 0.3.3()Z;		// selectingApplet()Z
		// 6
		virtualMethodRef 0.10.1()[B;		// getBuffer()[B
		// 7
		staticMethodRef 1.3.1(S)V;		// uicc/hci/framework/HCIException.throwIt(S)V
		// 8
		virtualMethodRef 1.3.1()S;		// getReason()S
		// 9
		staticMethodRef 0.7.1(S)V;		// javacard/framework/ISOException.throwIt(S)V
	}

	.class public Api_1_Hxp_Trw_1 0 extends 0.3 {		// extends javacard/framework/Applet

		.fields {
			private static final short SW_WRONG_EXECPTION = 28417;		// S
			private static final byte INS_EXP_HCI_ACCESS_NOT_GRANTED = 1;		// B
			private static final byte INS_EXP_HCI_CONDITION_NOT_SATISFIED = 2;		// B
			private static final byte INS_EXP_HCI_CURRENTLY_DISABLED = 3;		// B
			private static final byte INS_EXP_HCI_FRAGMENT_MSG_ONGOING = 4;		// B
			private static final byte INS_EXP_HCI_INVALID_LENGTH = 5;		// B
			private static final byte INS_EXP_HCI_LISTENER_ALREADY_REGISTERED = 6;		// B
			private static final byte INS_EXP_HCI_NOT_AVAILABLE = 7;		// B
			private static final byte INS_EXP_HCI_RESSOURCE_NOT_AVAILABLE = 8;		// B
			private static final byte INS_EXP_HCI_SERVICE_NOT_AVAILABLE = 9;		// B
			private static final byte INS_EXP_HCI_WRONG_EVENT_TYPE = 10;		// B
			private static final byte INS_EXP_HCI_WRONG_LISTENER_TYPE = 11;		// B
		}

		.publicMethodTable 7 {
			equals(Ljava/lang/Object;)Z;
			register()V;
			register([BSB)V;
			selectingApplet()Z;
			deselect()V;
			getShareableInterfaceObject(Ljavacard/framework/AID;B)Ljavacard/framework/Shareable;;
			select()Z;
			process(Ljavacard/framework/APDU;)V;
		}

		.packageMethodTable 0 {
		}

		.method private <init>()V {
			.stack 1;
			.locals 0;

				L0:	aload_0;
					invokespecial 0;		// javacard/framework/Applet.<init>()V
					aload_0;
					invokevirtual 1;		// register()V
					return;
		}

		.method public static install([BSB)V 0 {
			.stack 2;
			.locals 0;

				L0:	new 2;		// uicc/hci/test/framework/api_1_hxp_trw/Api_1_Hxp_Trw_1
					dup;
					invokespecial 3;		// uicc/hci/test/framework/api_1_hxp_trw/Api_1_Hxp_Trw_1.<init>()V
					pop;
					return;
		}

		.method public process(Ljavacard/framework/APDU;)V 7 {
			.stack 2;
			.locals 2;

			.descriptor	Ljavacard/framework/APDU;	0.10;

				L0:	aload_0;
					invokevirtual 5;		// selectingApplet()Z
					ifeq L2;
				L1:	return;
				L2:	aload_1;
					invokevirtual 6;		// getBuffer()[B
					astore_2;
					aload_2;
					sconst_1;
					baload;
					stableswitch L58 1 11 L3 L8 L13 L18 L23 L28 L33 L38 L43 L48 L53;
				L3:	sconst_1;
					invokestatic 7;		// uicc/hci/framework/HCIException.throwIt(S)V
				L4:	goto L7;
				L5:	astore_3;
					aload_3;
					invokevirtual 8;		// getReason()S
					sconst_1;
					if_scmpne L7;
				L6:	return;
				L7:	sspush 28417;
					invokestatic 9;		// javacard/framework/ISOException.throwIt(S)V
				L8:	bspush 10;
					invokestatic 7;		// uicc/hci/framework/HCIException.throwIt(S)V
				L9:	goto L12;
				L10:	astore_3;
					aload_3;
					invokevirtual 8;		// getReason()S
					bspush 10;
					if_scmpne L12;
				L11:	return;
				L12:	sspush 28417;
					invokestatic 9;		// javacard/framework/ISOException.throwIt(S)V
				L13:	sconst_3;
					invokestatic 7;		// uicc/hci/framework/HCIException.throwIt(S)V
				L14:	goto L17;
				L15:	astore_3;
					aload_3;
					invokevirtual 8;		// getReason()S
					sconst_3;
					if_scmpne L17;
				L16:	return;
				L17:	sspush 28417;
					invokestatic 9;		// javacard/framework/ISOException.throwIt(S)V
				L18:	bspush 7;
					invokestatic 7;		// uicc/hci/framework/HCIException.throwIt(S)V
				L19:	goto L22;
				L20:	astore_3;
					aload_3;
					invokevirtual 8;		// getReason()S
					bspush 7;
					if_scmpne L22;
				L21:	return;
				L22:	sspush 28417;
					invokestatic 9;		// javacard/framework/ISOException.throwIt(S)V
				L23:	bspush 9;
					invokestatic 7;		// uicc/hci/framework/HCIException.throwIt(S)V
				L24:	goto L27;
				L25:	astore_3;
					aload_3;
					invokevirtual 8;		// getReason()S
					bspush 9;
					if_scmpne L27;
				L26:	return;
				L27:	sspush 28417;
					invokestatic 9;		// javacard/framework/ISOException.throwIt(S)V
				L28:	sconst_5;
					invokestatic 7;		// uicc/hci/framework/HCIException.throwIt(S)V
				L29:	goto L32;
				L30:	astore_3;
					aload_3;
					invokevirtual 8;		// getReason()S
					sconst_5;
					if_scmpne L32;
				L31:	return;
				L32:	sspush 28417;
					invokestatic 9;		// javacard/framework/ISOException.throwIt(S)V
				L33:	sconst_0;
					invokestatic 7;		// uicc/hci/framework/HCIException.throwIt(S)V
				L34:	goto L37;
				L35:	astore_3;
					aload_3;
					invokevirtual 8;		// getReason()S
					ifne L37;
				L36:	return;
				L37:	sspush 28417;
					invokestatic 9;		// javacard/framework/ISOException.throwIt(S)V
				L38:	bspush 8;
					invokestatic 7;		// uicc/hci/framework/HCIException.throwIt(S)V
				L39:	goto L42;
				L40:	astore_3;
					aload_3;
					invokevirtual 8;		// getReason()S
					bspush 8;
					if_scmpne L42;
				L41:	return;
				L42:	sspush 28417;
					invokestatic 9;		// javacard/framework/ISOException.throwIt(S)V
				L43:	sconst_2;
					invokestatic 7;		// uicc/hci/framework/HCIException.throwIt(S)V
				L44:	goto L47;
				L45:	astore_3;
					aload_3;
					invokevirtual 8;		// getReason()S
					sconst_2;
					if_scmpne L47;
				L46:	return;
				L47:	sspush 28417;
					invokestatic 9;		// javacard/framework/ISOException.throwIt(S)V
				L48:	bspush 6;
					invokestatic 7;		// uicc/hci/framework/HCIException.throwIt(S)V
				L49:	goto L52;
				L50:	astore_3;
					aload_3;
					invokevirtual 8;		// getReason()S
					bspush 6;
					if_scmpne L52;
				L51:	return;
				L52:	sspush 28417;
					invokestatic 9;		// javacard/framework/ISOException.throwIt(S)V
				L53:	sconst_4;
					invokestatic 7;		// uicc/hci/framework/HCIException.throwIt(S)V
				L54:	goto L57;
				L55:	astore_3;
					aload_3;
					invokevirtual 8;		// getReason()S
					sconst_4;
					if_scmpne L57;
				L56:	return;
				L57:	sspush 28417;
					invokestatic 9;		// javacard/framework/ISOException.throwIt(S)V
				L58:	sspush 27904;
					invokestatic 9;		// javacard/framework/ISOException.throwIt(S)V
					return;
			.exceptionTable {
				// start_block end_block handler_block catch_type_index
				L3 L4 L5 4;
				L8 L9 L10 4;
				L13 L14 L15 4;
				L18 L19 L20 4;
				L23 L24 L25 4;
				L28 L29 L30 4;
				L33 L34 L35 4;
				L38 L39 L40 4;
				L43 L44 L45 4;
				L48 L49 L50 4;
				L53 L54 L55 4;
			}
		}

	}

}
