// converted by version  [v3.0.2]
// on Fri May 24 11:14:55 CEST 2013

.package uicc/hci/test/services/readermode/api_2_rmm_sgp {
	.aid 0xA0:0x0:0x0:0x0:0x9:0x0:0x5:0xFF:0xFF:0xFF:0xFF:0x89:0x27:0x3:0x0:0x0;
	.version 1.0;

	.imports {
		0xA0:0x0:0x0:0x0:0x62:0x1:0x1 1.4;		//javacard/framework
		0xA0:0x0:0x0:0x0:0x9:0x0:0x5:0xFF:0xFF:0xFF:0xFF:0x89:0x16:0x1:0x0:0x0 1.0;		//uicc/hci/framework
		0xA0:0x0:0x0:0x0:0x9:0x0:0x5:0xFF:0xFF:0xFF:0xFF:0x89:0x16:0x2:0x3:0x0 1.0;		//uicc/hci/services/readermode
		0xA0:0x0:0x0:0x0:0x62:0x0:0x1 1.0;		//java/lang
		0xA0:0x0:0x0:0x1:0x51:0x2 1.0;		//org/globalplatform/contactless
	}

	.applet {
		0xA0:0x0:0x0:0x0:0x9:0x0:0x5:0xFF:0xFF:0xFF:0xFF:0x89:0x27:0x3:0x1:0x2 Api_2_RMm_Sgp_1;
		0xA0:0x0:0x0:0x0:0x9:0x0:0x5:0xFF:0xFF:0xFF:0xFF:0x89:0x27:0x3:0x2:0x2 Api_2_RMm_Sgp_2;
		0xA0:0x0:0x0:0x0:0x9:0x0:0x5:0xFF:0xFF:0xFF:0xFF:0x89:0x27:0x3:0x3:0x2 Api_2_RMm_Sgp_3;
	}

	.constantPool {
		// 0
		instanceFieldRef 1.2 Api_2_RMm_Sgp_1/readerService;
		// 1
		instanceFieldRef boolean Api_2_RMm_Sgp_1/testSuccess;
		// 2
		instanceFieldRef byte Api_2_RMm_Sgp_1/featureToTest;
		// 3
		instanceFieldRef 2.2 Api_2_RMm_Sgp_2/readerService;
		// 4
		instanceFieldRef int Api_2_RMm_Sgp_2/featureToTest;
		// 5
		instanceFieldRef boolean Api_2_RMm_Sgp_2/exceptionHciDisabledThrown;
		// 6
		instanceFieldRef boolean Api_2_RMm_Sgp_2/exceptionReceivingHciThrown;
		// 7
		instanceFieldRef boolean Api_2_RMm_Sgp_2/exceptionIlligalValueThrown;
		// 8
		instanceFieldRef 2.2 Api_2_RMm_Sgp_3/readerService;
		// 9
		instanceFieldRef byte Api_2_RMm_Sgp_3/featureToTest;
		// 10
		instanceFieldRef boolean Api_2_RMm_Sgp_3/exceptionHciDisabledThrown;
		// 11
		instanceFieldRef boolean Api_2_RMm_Sgp_3/exceptionReceivingHciThrown;
		// 12
		instanceFieldRef boolean Api_2_RMm_Sgp_3/exceptionIlligalValueThrown;
		// 13
		virtualMethodRef 0.3.1()V;		// register()V
		// 14
		virtualMethodRef 0.10.8(SS)V;		// setOutgoingAndSend(SS)V
		// 15
		.classRef 2.1;		// uicc/hci/services/readermode/ReaderMessage
		// 16
		virtualMethodRef 0.3.1()V;		// register()V
		// 17
		staticMethodRef 1.4.0(S)Luicc/hci/framework/HCIService;;		// uicc/hci/framework/HCIDevice.getHCIService(S)Luicc/hci/framework/HCIService;
			.descriptor	Luicc/hci/framework/HCIService;	1.2;

		// 18
		.classRef Api_2_RMm_Sgp_2;
		// 19
		staticMethodRef Api_2_RMm_Sgp_2/<init>()V;
		// 20
		virtualMethodRef 0.3.3()Z;		// selectingApplet()Z
		// 21
		.classRef 2.2;		// uicc/hci/services/readermode/ReaderService
		// 22
		staticMethodRef 0.3.0()V;		// javacard/framework/Applet.<init>()V
		// 23
		.classRef 1.2;		// uicc/hci/framework/HCIService
		// 24
		staticMethodRef 0.7.1(S)V;		// javacard/framework/ISOException.throwIt(S)V
		// 25
		.classRef 0.13;		// javacard/framework/SystemException
		// 26
		virtualMethodRef 1.3.1()S;		// getReason()S
		// 27
		virtualMethodRef 0.13.1()S;		// getReason()S
		// 28
		virtualMethodRef 0.3.1()V;		// register()V
		// 29
		.classRef Api_2_RMm_Sgp_1;
		// 30
		.classRef Api_2_RMm_Sgp_3;
		// 31
		staticMethodRef Api_2_RMm_Sgp_3/<init>()V;
		// 32
		virtualMethodRef 0.3.3()Z;		// selectingApplet()Z
		// 33
		staticMethodRef Api_2_RMm_Sgp_1/<init>()V;
		// 34
		virtualMethodRef 0.3.3()Z;		// selectingApplet()Z
		// 35
		virtualMethodRef 0.10.1()[B;		// getBuffer()[B
		// 36
		.classRef 1.3;		// uicc/hci/framework/HCIException
		// 37
		staticMethodRef 4.5.4(SZ)V;		// org/globalplatform/contactless/GPCLSystem.setCommunicationInterface(SZ)V
	}

	.class public Api_2_RMm_Sgp_1 0 extends 0.3 {		// extends javacard/framework/Applet

		.shareable;

		.fields {
			private 1.2 readerService 0;		// Luicc/hci/framework/HCIService;
			private byte featureToTest 1;		// B
			private boolean testSuccess 2;		// Z
			private static final byte INS_GET_TYPE_A_UID = 1;		// B
			private static final byte INS_GET_TYPE_A_ATQA = 2;		// B
			private static final byte INS_GET_TYPE_A_APP_DATA = 3;		// B
			private static final byte INS_GET_TYPE_A_SAK = 4;		// B
			private static final byte INS_GET_TYPE_A_FWI = 5;		// B
			private static final byte INS_GET_TYPE_A_DATA_R_MAX = 6;		// B
			private static final byte INS_GET_TYPE_B_PUPI = 7;		// B
			private static final byte INS_GET_TYPE_B_APP_DATA = 8;		// B
			private static final byte INS_GET_TYPE_B_AFI = 9;		// B
			private static final byte INS_GET_TYPE_B_HIGHER_LAYER_RESPONSE = 10;		// B
			private static final byte INS_GET_TYPE_B_HIGHER_LAYER_DATA = 11;		// B
		}

		.publicMethodTable 7 {
			equals(Ljava/lang/Object;)Z;
			register()V;
			register([BSB)V;
			selectingApplet()Z;
			deselect()V;
			getShareableInterfaceObject(Ljavacard/framework/AID;B)Ljavacard/framework/Shareable;;
			select()Z;
			process(Ljavacard/framework/APDU;)V;
			onCallback(BLuicc/hci/framework/HCIMessage;)V;
		}

		.packageMethodTable 0 {
		}

		.implementedInterfaceInfoTable { 
			.interface 0.2 { 		// javacard/framework/Shareable
			}

			.interface 1.0 { 		// uicc/hci/framework/HCIListener
				8;		// onCallback(BLuicc/hci/framework/HCIMessage;)V
			}

			.interface 2.0 { 		// uicc/hci/services/readermode/ReaderListener
				8;		// onCallback(BLuicc/hci/framework/HCIMessage;)V
			}

		}

		.method public <init>()V 0 {
			.stack 2;
			.locals 1;

				L0:	aload_0;
					invokespecial 22;		// javacard/framework/Applet.<init>()V
					aload_0;
					invokevirtual 13;		// register()V
				L1:	aload_0;
					sconst_2;
					invokestatic 17;		// uicc/hci/framework/HCIDevice.getHCIService(S)Luicc/hci/framework/HCIService;
					checkcast 0 21;		// T_CLASSORINTERFACE uicc/hci/services/readermode/ReaderService
					putfield_a 0;		// reference uicc/hci/test/services/readermode/api_2_rmm_sgp/Api_2_RMm_Sgp_1.readerService
					getfield_a_this 0;		// reference uicc/hci/test/services/readermode/api_2_rmm_sgp/Api_2_RMm_Sgp_1.readerService
					aload_0;
					invokeinterface 2 23 0;		// uicc/hci/framework/HCIService
					getfield_a_this 0;		// reference uicc/hci/test/services/readermode/api_2_rmm_sgp/Api_2_RMm_Sgp_1.readerService
					sconst_1;
					invokeinterface 2 23 3;		// uicc/hci/framework/HCIService
				L2:	goto L4;
				L3:	astore_1;
					sspush 27012;
					invokestatic 24;		// javacard/framework/ISOException.throwIt(S)V
				L4:	return;
			.exceptionTable {
				// start_block end_block handler_block catch_type_index
				L1 L2 L3 36;
			}
		}

		.method public static install([BSB)V 1 {
			.stack 2;
			.locals 0;

				L0:	new 29;		// uicc/hci/test/services/readermode/api_2_rmm_sgp/Api_2_RMm_Sgp_1
					dup;
					invokespecial 33;		// uicc/hci/test/services/readermode/api_2_rmm_sgp/Api_2_RMm_Sgp_1.<init>()V
					pop;
					return;
		}

		.method public process(Ljavacard/framework/APDU;)V 7 {
			.stack 3;
			.locals 2;

			.descriptor	Ljavacard/framework/APDU;	0.10;

				L0:	aload_0;
					invokevirtual 34;		// selectingApplet()Z
					ifeq L2;
				L1:	getfield_a_this 0;		// reference uicc/hci/test/services/readermode/api_2_rmm_sgp/Api_2_RMm_Sgp_1.readerService
					bspush 80;
					invokeinterface 2 23 3;		// uicc/hci/framework/HCIService
					return;
				L2:	aload_1;
					invokevirtual 35;		// getBuffer()[B
					astore_2;
					aload_2;
					sconst_1;
					baload;
					sstore_3;
					sload_3;
					sconst_1;
					if_scmplt L5;
				L3:	sload_3;
					bspush 11;
					if_scmpgt L5;
				L4:	aload_0;
					sconst_0;
					putfield_b 1;		// boolean uicc/hci/test/services/readermode/api_2_rmm_sgp/Api_2_RMm_Sgp_1.testSuccess
					aload_0;
					aload_2;
					sconst_1;
					baload;
					putfield_b 2;		// byte uicc/hci/test/services/readermode/api_2_rmm_sgp/Api_2_RMm_Sgp_1.featureToTest
					return;
				L5:	sload_3;
					bspush 32;
					if_scmpne L10;
				L6:	aload_2;
					sconst_0;
					getfield_b_this 2;		// byte uicc/hci/test/services/readermode/api_2_rmm_sgp/Api_2_RMm_Sgp_1.featureToTest
					bastore;
					aload_2;
					sconst_1;
					getfield_b_this 1;		// boolean uicc/hci/test/services/readermode/api_2_rmm_sgp/Api_2_RMm_Sgp_1.testSuccess
					ifeq L8;
				L7:	sconst_0;
					goto L9;
				L8:	sconst_1;
				L9:	bastore;
					aload_1;
					sconst_0;
					sconst_2;
					invokevirtual 14;		// setOutgoingAndSend(SS)V
				L10:	return;
		}

		.method public onCallback(BLuicc/hci/framework/HCIMessage;)V 8 {
			.stack 3;
			.locals 3;

			.descriptor	Luicc/hci/framework/HCIMessage;	1.1;

				L0:	aload_2;
					checkcast 0 15;		// T_CLASSORINTERFACE uicc/hci/services/readermode/ReaderMessage
					astore_3;
					aload_3;
					invokeinterface 1 15 2;		// uicc/hci/services/readermode/ReaderMessage
					bspush 64;
					if_scmpne L18;
				L1:	sload_1;
					bspush 80;
					if_scmpne_w L64;
				L2:	aload_3;
					invokeinterface 1 15 4;		// uicc/hci/services/readermode/ReaderMessage
					sconst_0;
					baload;
					sstore 4;
					sload 4;
					ifne L17;
				L3:	getfield_b_this 2;		// byte uicc/hci/test/services/readermode/api_2_rmm_sgp/Api_2_RMm_Sgp_1.featureToTest
					stableswitch L15 1 11 L4 L5 L6 L7 L8 L9 L10 L11 L12 L13 L14;
				L4:	sconst_2;
					sstore 5;
					goto L16;
				L5:	sconst_4;
					sstore 5;
					goto L16;
				L6:	sconst_5;
					sstore 5;
					goto L16;
				L7:	sconst_3;
					sstore 5;
					goto L16;
				L8:	bspush 6;
					sstore 5;
					goto L16;
				L9:	sconst_1;
					sstore 5;
					goto L16;
				L10:	sconst_3;
					sstore 5;
					goto L16;
				L11:	sconst_4;
					sstore 5;
					goto L16;
				L12:	sconst_2;
					sstore 5;
					goto L16;
				L13:	sconst_1;
					sstore 5;
					goto L16;
				L14:	sconst_5;
					sstore 5;
					goto L16;
				L15:	sconst_m1;
					sstore 5;
				L16:	aload_3;
					sload 5;
					invokeinterface 2 15 7;		// uicc/hci/services/readermode/ReaderMessage
				L17:	goto_w L64;
				L18:	aload_3;
					invokeinterface 1 15 2;		// uicc/hci/services/readermode/ReaderMessage
					bspush -128;
					if_scmpne_w L64;
				L19:	getfield_b_this 2;		// byte uicc/hci/test/services/readermode/api_2_rmm_sgp/Api_2_RMm_Sgp_1.featureToTest
					stableswitch L64 1 11 L20 L24 L28 L32 L36 L40 L44 L48 L52 L56 L60;
				L20:	aload_0;
					aload_3;
					invokeinterface 1 15 4;		// uicc/hci/services/readermode/ReaderMessage
					sconst_0;
					baload;
					sconst_2;
					if_scmpne L22;
				L21:	sconst_1;
					goto L23;
				L22:	sconst_0;
				L23:	putfield_b 1;		// boolean uicc/hci/test/services/readermode/api_2_rmm_sgp/Api_2_RMm_Sgp_1.testSuccess
					goto_w L64;
				L24:	aload_0;
					aload_3;
					invokeinterface 1 15 4;		// uicc/hci/services/readermode/ReaderMessage
					sconst_0;
					baload;
					sconst_4;
					if_scmpne L26;
				L25:	sconst_1;
					goto L27;
				L26:	sconst_0;
				L27:	putfield_b 1;		// boolean uicc/hci/test/services/readermode/api_2_rmm_sgp/Api_2_RMm_Sgp_1.testSuccess
					goto_w L64;
				L28:	aload_0;
					aload_3;
					invokeinterface 1 15 4;		// uicc/hci/services/readermode/ReaderMessage
					sconst_0;
					baload;
					sconst_5;
					if_scmpne L30;
				L29:	sconst_1;
					goto L31;
				L30:	sconst_0;
				L31:	putfield_b 1;		// boolean uicc/hci/test/services/readermode/api_2_rmm_sgp/Api_2_RMm_Sgp_1.testSuccess
					goto_w L64;
				L32:	aload_0;
					aload_3;
					invokeinterface 1 15 4;		// uicc/hci/services/readermode/ReaderMessage
					sconst_0;
					baload;
					sconst_3;
					if_scmpne L34;
				L33:	sconst_1;
					goto L35;
				L34:	sconst_0;
				L35:	putfield_b 1;		// boolean uicc/hci/test/services/readermode/api_2_rmm_sgp/Api_2_RMm_Sgp_1.testSuccess
					goto_w L64;
				L36:	aload_0;
					aload_3;
					invokeinterface 1 15 4;		// uicc/hci/services/readermode/ReaderMessage
					sconst_0;
					baload;
					bspush 6;
					if_scmpne L38;
				L37:	sconst_1;
					goto L39;
				L38:	sconst_0;
				L39:	putfield_b 1;		// boolean uicc/hci/test/services/readermode/api_2_rmm_sgp/Api_2_RMm_Sgp_1.testSuccess
					goto L64;
				L40:	aload_0;
					aload_3;
					invokeinterface 1 15 4;		// uicc/hci/services/readermode/ReaderMessage
					sconst_0;
					baload;
					sconst_1;
					if_scmpne L42;
				L41:	sconst_1;
					goto L43;
				L42:	sconst_0;
				L43:	putfield_b 1;		// boolean uicc/hci/test/services/readermode/api_2_rmm_sgp/Api_2_RMm_Sgp_1.testSuccess
					goto L64;
				L44:	aload_0;
					aload_3;
					invokeinterface 1 15 4;		// uicc/hci/services/readermode/ReaderMessage
					sconst_0;
					baload;
					sconst_3;
					if_scmpne L46;
				L45:	sconst_1;
					goto L47;
				L46:	sconst_0;
				L47:	putfield_b 1;		// boolean uicc/hci/test/services/readermode/api_2_rmm_sgp/Api_2_RMm_Sgp_1.testSuccess
					goto L64;
				L48:	aload_0;
					aload_3;
					invokeinterface 1 15 4;		// uicc/hci/services/readermode/ReaderMessage
					sconst_0;
					baload;
					sconst_4;
					if_scmpne L50;
				L49:	sconst_1;
					goto L51;
				L50:	sconst_0;
				L51:	putfield_b 1;		// boolean uicc/hci/test/services/readermode/api_2_rmm_sgp/Api_2_RMm_Sgp_1.testSuccess
					goto L64;
				L52:	aload_0;
					aload_3;
					invokeinterface 1 15 4;		// uicc/hci/services/readermode/ReaderMessage
					sconst_0;
					baload;
					sconst_2;
					if_scmpne L54;
				L53:	sconst_1;
					goto L55;
				L54:	sconst_0;
				L55:	putfield_b 1;		// boolean uicc/hci/test/services/readermode/api_2_rmm_sgp/Api_2_RMm_Sgp_1.testSuccess
					goto L64;
				L56:	aload_0;
					aload_3;
					invokeinterface 1 15 4;		// uicc/hci/services/readermode/ReaderMessage
					sconst_0;
					baload;
					sconst_1;
					if_scmpne L58;
				L57:	sconst_1;
					goto L59;
				L58:	sconst_0;
				L59:	putfield_b 1;		// boolean uicc/hci/test/services/readermode/api_2_rmm_sgp/Api_2_RMm_Sgp_1.testSuccess
					goto L64;
				L60:	aload_0;
					aload_3;
					invokeinterface 1 15 4;		// uicc/hci/services/readermode/ReaderMessage
					sconst_0;
					baload;
					sconst_5;
					if_scmpne L62;
				L61:	sconst_1;
					goto L63;
				L62:	sconst_0;
				L63:	putfield_b 1;		// boolean uicc/hci/test/services/readermode/api_2_rmm_sgp/Api_2_RMm_Sgp_1.testSuccess
				L64:	return;
		}

	}

	.class public Api_2_RMm_Sgp_2 1 extends 0.3 {		// extends javacard/framework/Applet

		.shareable;

		.fields {
			private 2.2 readerService 0;		// Luicc/hci/services/readermode/ReaderService;
			private int featureToTest 1;		// I
			private boolean exceptionHciDisabledThrown 3;		// Z
			private boolean exceptionIlligalValueThrown 4;		// Z
			private boolean exceptionReceivingHciThrown 5;		// Z
			private static final byte INS_TEST_HCI_DISABLED = 1;		// B
			private static final byte INS_TEST_RECEIVING_HCI_MESSAGE = 2;		// B
			private static final byte INS_TEST_ILLIGALVALUE = 5;		// B
			private static final byte INS_VERIFY_HCI_DISABLED = 17;		// B
			private static final byte INS_VERIFY_RECEIVING_HCI_MESSAGE = 18;		// B
			private static final byte INS_VERIFY_ILLIGALVALUE = 21;		// B
		}

		.publicMethodTable 7 {
			equals(Ljava/lang/Object;)Z;
			register()V;
			register([BSB)V;
			selectingApplet()Z;
			deselect()V;
			getShareableInterfaceObject(Ljavacard/framework/AID;B)Ljavacard/framework/Shareable;;
			select()Z;
			process(Ljavacard/framework/APDU;)V;
			onCallback(BLuicc/hci/framework/HCIMessage;)V;
		}

		.packageMethodTable 0 {
		}

		.implementedInterfaceInfoTable { 
			.interface 0.2 { 		// javacard/framework/Shareable
			}

			.interface 1.0 { 		// uicc/hci/framework/HCIListener
				8;		// onCallback(BLuicc/hci/framework/HCIMessage;)V
			}

			.interface 2.0 { 		// uicc/hci/services/readermode/ReaderListener
				8;		// onCallback(BLuicc/hci/framework/HCIMessage;)V
			}

		}

		.method public <init>()V 0 {
			.stack 2;
			.locals 1;

				L0:	aload_0;
					invokespecial 22;		// javacard/framework/Applet.<init>()V
					aload_0;
					invokevirtual 16;		// register()V
				L1:	aload_0;
					sconst_2;
					invokestatic 17;		// uicc/hci/framework/HCIDevice.getHCIService(S)Luicc/hci/framework/HCIService;
					checkcast 0 21;		// T_CLASSORINTERFACE uicc/hci/services/readermode/ReaderService
					putfield_a 3;		// reference uicc/hci/test/services/readermode/api_2_rmm_sgp/Api_2_RMm_Sgp_2.readerService
					getfield_a_this 3;		// reference uicc/hci/test/services/readermode/api_2_rmm_sgp/Api_2_RMm_Sgp_2.readerService
					aload_0;
					invokeinterface 2 21 0;		// uicc/hci/services/readermode/ReaderService
				L2:	goto L4;
				L3:	astore_1;
					sspush 27012;
					invokestatic 24;		// javacard/framework/ISOException.throwIt(S)V
				L4:	return;
			.exceptionTable {
				// start_block end_block handler_block catch_type_index
				L1 L2 L3 36;
			}
		}

		.method public static install([BSB)V 1 {
			.stack 2;
			.locals 0;

				L0:	new 18;		// uicc/hci/test/services/readermode/api_2_rmm_sgp/Api_2_RMm_Sgp_2
					dup;
					invokespecial 19;		// uicc/hci/test/services/readermode/api_2_rmm_sgp/Api_2_RMm_Sgp_2.<init>()V
					pop;
					return;
		}

		.method public process(Ljavacard/framework/APDU;)V 7 {
			.stack 3;
			.locals 1;

			.descriptor	Ljavacard/framework/APDU;	0.10;

				L0:	aload_0;
					invokevirtual 20;		// selectingApplet()Z
					ifeq L2;
				L1:	getfield_a_this 3;		// reference uicc/hci/test/services/readermode/api_2_rmm_sgp/Api_2_RMm_Sgp_2.readerService
					bspush 80;
					invokeinterface 2 21 3;		// uicc/hci/services/readermode/ReaderService
					return;
				L2:	aload_1;
					invokevirtual 35;		// getBuffer()[B
					astore_2;
					aload_2;
					sconst_1;
					baload;
					slookupswitch L12 6 1 L3 2 L4 5 L5 17 L6 18 L8 21 L10;
				L3:	aload_0;
					iconst_1;
					putfield_i 4;		// int uicc/hci/test/services/readermode/api_2_rmm_sgp/Api_2_RMm_Sgp_2.featureToTest
					goto L12;
				L4:	aload_0;
					iconst_2;
					putfield_i 4;		// int uicc/hci/test/services/readermode/api_2_rmm_sgp/Api_2_RMm_Sgp_2.featureToTest
					goto L12;
				L5:	aload_0;
					iconst_5;
					putfield_i 4;		// int uicc/hci/test/services/readermode/api_2_rmm_sgp/Api_2_RMm_Sgp_2.featureToTest
					goto L12;
				L6:	getfield_b_this 5;		// boolean uicc/hci/test/services/readermode/api_2_rmm_sgp/Api_2_RMm_Sgp_2.exceptionHciDisabledThrown
					ifeq L12;
				L7:	sspush -28669;
					invokestatic 24;		// javacard/framework/ISOException.throwIt(S)V
					goto L12;
				L8:	getfield_b_this 6;		// boolean uicc/hci/test/services/readermode/api_2_rmm_sgp/Api_2_RMm_Sgp_2.exceptionReceivingHciThrown
					ifeq L12;
				L9:	sspush -28668;
					invokestatic 24;		// javacard/framework/ISOException.throwIt(S)V
					goto L12;
				L10:	getfield_b_this 7;		// boolean uicc/hci/test/services/readermode/api_2_rmm_sgp/Api_2_RMm_Sgp_2.exceptionIlligalValueThrown
					ifeq L12;
				L11:	sspush -28667;
					invokestatic 24;		// javacard/framework/ISOException.throwIt(S)V
				L12:	return;
		}

		.method public onCallback(BLuicc/hci/framework/HCIMessage;)V 8 {
			.stack 4;
			.locals 3;

			.descriptor	Luicc/hci/framework/HCIMessage;	1.1;

				L0:	aload_2;
					checkcast 0 15;		// T_CLASSORINTERFACE uicc/hci/services/readermode/ReaderMessage
					astore_3;
					aload_3;
					invokeinterface 1 15 2;		// uicc/hci/services/readermode/ReaderMessage
					bspush 64;
					if_scmpne_w L19;
				L1:	sload_1;
					bspush 80;
					if_scmpne_w L19;
				L2:	aload_3;
					invokeinterface 1 15 4;		// uicc/hci/services/readermode/ReaderMessage
					sconst_0;
					baload;
					slookupswitch L19 1 0 L3;
				L3:	sconst_0;
					sstore 4;
					getfield_i_this 4;		// int uicc/hci/test/services/readermode/api_2_rmm_sgp/Api_2_RMm_Sgp_2.featureToTest
					itableswitch L7 1 5 L4 L5 L7 L7 L6;
				L4:	goto L7;
				L5:	sconst_2;
					sstore 4;
					goto L7;
				L6:	sconst_m1;
					sstore 4;
				L7:	aload_3;
					sload 4;
					invokeinterface 2 15 7;		// uicc/hci/services/readermode/ReaderMessage
				L8:	goto L19;
				L9:	astore 5;
					aload 5;
					invokevirtual 26;		// getReason()S
					sconst_3;
					if_scmpne L12;
				L10:	getfield_i_this 4;		// int uicc/hci/test/services/readermode/api_2_rmm_sgp/Api_2_RMm_Sgp_2.featureToTest
					iconst_1;
					icmp;
					ifne L15;
				L11:	aload_0;
					sconst_1;
					putfield_b 5;		// boolean uicc/hci/test/services/readermode/api_2_rmm_sgp/Api_2_RMm_Sgp_2.exceptionHciDisabledThrown
					goto L15;
				L12:	aload 5;
					invokevirtual 26;		// getReason()S
					bspush 7;
					if_scmpne L15;
				L13:	getfield_i_this 4;		// int uicc/hci/test/services/readermode/api_2_rmm_sgp/Api_2_RMm_Sgp_2.featureToTest
					iconst_2;
					icmp;
					ifne L15;
				L14:	aload_0;
					sconst_1;
					putfield_b 6;		// boolean uicc/hci/test/services/readermode/api_2_rmm_sgp/Api_2_RMm_Sgp_2.exceptionReceivingHciThrown
				L15:	goto L19;
				L16:	astore 5;
					aload 5;
					invokevirtual 27;		// getReason()S
					sconst_1;
					if_scmpne L19;
				L17:	getfield_i_this 4;		// int uicc/hci/test/services/readermode/api_2_rmm_sgp/Api_2_RMm_Sgp_2.featureToTest
					iconst_5;
					icmp;
					ifne L19;
				L18:	aload_0;
					sconst_1;
					putfield_b 7;		// boolean uicc/hci/test/services/readermode/api_2_rmm_sgp/Api_2_RMm_Sgp_2.exceptionIlligalValueThrown
				L19:	return;
			.exceptionTable {
				// start_block end_block handler_block catch_type_index
				L7 L8 L9 36;
				L7 L8 L16 25;
			}
		}

	}

	.class public Api_2_RMm_Sgp_3 2 extends 0.3 {		// extends javacard/framework/Applet

		.shareable;

		.fields {
			private 2.2 readerService 0;		// Luicc/hci/services/readermode/ReaderService;
			private byte featureToTest 1;		// B
			private boolean exceptionHciDisabledThrown 2;		// Z
			private boolean exceptionIlligalValueThrown 3;		// Z
			private boolean exceptionReceivingHciThrown 4;		// Z
			private static final byte INS_TEST_HCI_DISABLED = 1;		// B
			private static final byte INS_TEST_RECEIVING_HCI_MESSAGE = 2;		// B
			private static final byte INS_TEST_ILLIGALVALUE = 5;		// B
			private static final byte INS_VERIFY_HCI_DISABLED = 17;		// B
			private static final byte INS_VERIFY_RECEIVING_HCI_MESSAGE = 18;		// B
			private static final byte INS_VERIFY_ILLIGALVALUE = 21;		// B
		}

		.publicMethodTable 7 {
			equals(Ljava/lang/Object;)Z;
			register()V;
			register([BSB)V;
			selectingApplet()Z;
			deselect()V;
			getShareableInterfaceObject(Ljavacard/framework/AID;B)Ljavacard/framework/Shareable;;
			select()Z;
			process(Ljavacard/framework/APDU;)V;
			onCallback(BLuicc/hci/framework/HCIMessage;)V;
			uninstall()V;
		}

		.packageMethodTable 0 {
		}

		.implementedInterfaceInfoTable { 
			.interface 0.2 { 		// javacard/framework/Shareable
			}

			.interface 1.0 { 		// uicc/hci/framework/HCIListener
				8;		// onCallback(BLuicc/hci/framework/HCIMessage;)V
			}

			.interface 2.0 { 		// uicc/hci/services/readermode/ReaderListener
				8;		// onCallback(BLuicc/hci/framework/HCIMessage;)V
			}

		}

		.method public <init>()V 0 {
			.stack 2;
			.locals 1;

				L0:	aload_0;
					invokespecial 22;		// javacard/framework/Applet.<init>()V
					aload_0;
					invokevirtual 28;		// register()V
				L1:	aload_0;
					sconst_2;
					invokestatic 17;		// uicc/hci/framework/HCIDevice.getHCIService(S)Luicc/hci/framework/HCIService;
					checkcast 0 21;		// T_CLASSORINTERFACE uicc/hci/services/readermode/ReaderService
					putfield_a 8;		// reference uicc/hci/test/services/readermode/api_2_rmm_sgp/Api_2_RMm_Sgp_3.readerService
					getfield_a_this 8;		// reference uicc/hci/test/services/readermode/api_2_rmm_sgp/Api_2_RMm_Sgp_3.readerService
					aload_0;
					invokeinterface 2 21 0;		// uicc/hci/services/readermode/ReaderService
				L2:	goto L4;
				L3:	astore_1;
					sspush 27012;
					invokestatic 24;		// javacard/framework/ISOException.throwIt(S)V
				L4:	return;
			.exceptionTable {
				// start_block end_block handler_block catch_type_index
				L1 L2 L3 36;
			}
		}

		.method public static install([BSB)V 1 {
			.stack 2;
			.locals 0;

				L0:	new 30;		// uicc/hci/test/services/readermode/api_2_rmm_sgp/Api_2_RMm_Sgp_3
					dup;
					invokespecial 31;		// uicc/hci/test/services/readermode/api_2_rmm_sgp/Api_2_RMm_Sgp_3.<init>()V
					pop;
					return;
		}

		.method public process(Ljavacard/framework/APDU;)V 7 {
			.stack 2;
			.locals 1;

			.descriptor	Ljavacard/framework/APDU;	0.10;

				L0:	aload_0;
					invokevirtual 32;		// selectingApplet()Z
					ifeq L2;
				L1:	getfield_a_this 8;		// reference uicc/hci/test/services/readermode/api_2_rmm_sgp/Api_2_RMm_Sgp_3.readerService
					bspush 80;
					invokeinterface 2 21 3;		// uicc/hci/services/readermode/ReaderService
					return;
				L2:	aload_1;
					invokevirtual 35;		// getBuffer()[B
					astore_2;
					aload_2;
					sconst_1;
					baload;
					slookupswitch L12 6 1 L3 2 L4 5 L5 17 L6 18 L8 21 L10;
				L3:	aload_0;
					sconst_1;
					putfield_b 9;		// byte uicc/hci/test/services/readermode/api_2_rmm_sgp/Api_2_RMm_Sgp_3.featureToTest
					goto L12;
				L4:	aload_0;
					sconst_2;
					putfield_b 9;		// byte uicc/hci/test/services/readermode/api_2_rmm_sgp/Api_2_RMm_Sgp_3.featureToTest
					goto L12;
				L5:	aload_0;
					sconst_5;
					putfield_b 9;		// byte uicc/hci/test/services/readermode/api_2_rmm_sgp/Api_2_RMm_Sgp_3.featureToTest
					goto L12;
				L6:	getfield_b_this 10;		// boolean uicc/hci/test/services/readermode/api_2_rmm_sgp/Api_2_RMm_Sgp_3.exceptionHciDisabledThrown
					ifeq L12;
				L7:	sspush -28669;
					invokestatic 24;		// javacard/framework/ISOException.throwIt(S)V
					goto L12;
				L8:	getfield_b_this 11;		// boolean uicc/hci/test/services/readermode/api_2_rmm_sgp/Api_2_RMm_Sgp_3.exceptionReceivingHciThrown
					ifeq L12;
				L9:	sspush -28668;
					invokestatic 24;		// javacard/framework/ISOException.throwIt(S)V
					goto L12;
				L10:	getfield_b_this 12;		// boolean uicc/hci/test/services/readermode/api_2_rmm_sgp/Api_2_RMm_Sgp_3.exceptionIlligalValueThrown
					ifeq L12;
				L11:	sspush -28667;
					invokestatic 24;		// javacard/framework/ISOException.throwIt(S)V
				L12:	return;
		}

		.method public onCallback(BLuicc/hci/framework/HCIMessage;)V 8 {
			.stack 2;
			.locals 3;

			.descriptor	Luicc/hci/framework/HCIMessage;	1.1;

				L0:	aload_2;
					checkcast 0 15;		// T_CLASSORINTERFACE uicc/hci/services/readermode/ReaderMessage
					astore_3;
					aload_3;
					invokeinterface 1 15 2;		// uicc/hci/services/readermode/ReaderMessage
					bspush 64;
					if_scmpne_w L19;
				L1:	sload_1;
					bspush 80;
					if_scmpne_w L19;
				L2:	aload_3;
					invokeinterface 1 15 3;		// uicc/hci/services/readermode/ReaderMessage
					slookupswitch L19 1 0 L3;
				L3:	sconst_0;
					sstore 4;
					getfield_b_this 9;		// byte uicc/hci/test/services/readermode/api_2_rmm_sgp/Api_2_RMm_Sgp_3.featureToTest
					stableswitch L7 1 5 L4 L5 L7 L7 L6;
				L4:	sconst_1;
					sconst_0;
					invokestatic 37;		// org/globalplatform/contactless/GPCLSystem.setCommunicationInterface(SZ)V
					goto L7;
				L5:	sconst_2;
					sstore 4;
					goto L7;
				L6:	sconst_m1;
					sstore 4;
				L7:	aload_3;
					sload 4;
					invokeinterface 2 15 7;		// uicc/hci/services/readermode/ReaderMessage
				L8:	goto L19;
				L9:	astore 5;
					aload 5;
					invokevirtual 26;		// getReason()S
					sconst_3;
					if_scmpne L12;
				L10:	getfield_b_this 9;		// byte uicc/hci/test/services/readermode/api_2_rmm_sgp/Api_2_RMm_Sgp_3.featureToTest
					sconst_1;
					if_scmpne L15;
				L11:	aload_0;
					sconst_1;
					putfield_b 10;		// boolean uicc/hci/test/services/readermode/api_2_rmm_sgp/Api_2_RMm_Sgp_3.exceptionHciDisabledThrown
					goto L15;
				L12:	aload 5;
					invokevirtual 26;		// getReason()S
					bspush 7;
					if_scmpne L15;
				L13:	getfield_b_this 9;		// byte uicc/hci/test/services/readermode/api_2_rmm_sgp/Api_2_RMm_Sgp_3.featureToTest
					sconst_2;
					if_scmpne L15;
				L14:	aload_0;
					sconst_1;
					putfield_b 11;		// boolean uicc/hci/test/services/readermode/api_2_rmm_sgp/Api_2_RMm_Sgp_3.exceptionReceivingHciThrown
				L15:	goto L19;
				L16:	astore 5;
					aload 5;
					invokevirtual 27;		// getReason()S
					sconst_1;
					if_scmpne L19;
				L17:	getfield_b_this 9;		// byte uicc/hci/test/services/readermode/api_2_rmm_sgp/Api_2_RMm_Sgp_3.featureToTest
					sconst_5;
					if_scmpne L19;
				L18:	aload_0;
					sconst_1;
					putfield_b 12;		// boolean uicc/hci/test/services/readermode/api_2_rmm_sgp/Api_2_RMm_Sgp_3.exceptionIlligalValueThrown
				L19:	return;
			.exceptionTable {
				// start_block end_block handler_block catch_type_index
				L7 L8 L9 36;
				L7 L8 L16 25;
			}
		}

		.method public uninstall()V 9 {
			.stack 2;
			.locals 0;

				L0:	sconst_1;
					sconst_1;
					invokestatic 37;		// org/globalplatform/contactless/GPCLSystem.setCommunicationInterface(SZ)V
					return;
		}

	}

}
