// converted by version  [v3.0.2]
// on Fri May 24 11:14:39 CEST 2013

.package uicc/hci/test/framework/api_1_hdv_gsr {
	.aid 0xA0:0x0:0x0:0x0:0x9:0x0:0x5:0xFF:0xFF:0xFF:0xFF:0x89:0x21:0x0:0x0:0x0;
	.version 1.0;

	.imports {
		0xA0:0x0:0x0:0x0:0x62:0x1:0x1 1.4;		//javacard/framework
		0xA0:0x0:0x0:0x0:0x9:0x0:0x5:0xFF:0xFF:0xFF:0xFF:0x89:0x16:0x1:0x0:0x0 1.0;		//uicc/hci/framework
		0xA0:0x0:0x0:0x0:0x9:0x0:0x5:0xFF:0xFF:0xFF:0xFF:0x89:0x16:0x2:0x1:0x0 1.0;		//uicc/hci/services/cardemulation
		0xA0:0x0:0x0:0x0:0x9:0x0:0x5:0xFF:0xFF:0xFF:0xFF:0x89:0x16:0x2:0x2:0x0 1.0;		//uicc/hci/services/connectivity
		0xA0:0x0:0x0:0x0:0x9:0x0:0x5:0xFF:0xFF:0xFF:0xFF:0x89:0x16:0x2:0x3:0x0 1.0;		//uicc/hci/services/readermode
		0xA0:0x0:0x0:0x0:0x62:0x0:0x1 1.0;		//java/lang
	}

	.applet {
		0xA0:0x0:0x0:0x0:0x9:0x0:0x5:0xFF:0xFF:0xFF:0xFF:0x89:0x21:0x1:0x1:0x2 Api_1_Hdv_Gsr_1;
		0xA0:0x0:0x0:0x0:0x9:0x0:0x5:0xFF:0xFF:0xFF:0xFF:0x89:0x21:0x1:0x2:0x2 Api_1_Hdv_Gsr_2;
	}

	.constantPool {
		// 0
		instanceFieldRef 2.2 Api_1_Hdv_Gsr_1/ceService;
		// 1
		instanceFieldRef 3.2 Api_1_Hdv_Gsr_1/cnnService;
		// 2
		instanceFieldRef 4.2 Api_1_Hdv_Gsr_1/rmService;
		// 3
		instanceFieldRef boolean Api_1_Hdv_Gsr_2/isNoServiceBeforeRegister;
		// 4
		.classRef 1.3;		// uicc/hci/framework/HCIException
		// 5
		.classRef 0.13;		// javacard/framework/SystemException
		// 6
		virtualMethodRef 0.3.3()Z;		// selectingApplet()Z
		// 7
		virtualMethodRef 0.10.1()[B;		// getBuffer()[B
		// 8
		staticMethodRef 1.4.0(S)Luicc/hci/framework/HCIService;;		// uicc/hci/framework/HCIDevice.getHCIService(S)Luicc/hci/framework/HCIService;
			.descriptor	Luicc/hci/framework/HCIService;	1.2;

		// 9
		.classRef 2.2;		// uicc/hci/services/cardemulation/CardEmulationService
		// 10
		staticMethodRef 0.3.0()V;		// javacard/framework/Applet.<init>()V
		// 11
		staticMethodRef 0.7.1(S)V;		// javacard/framework/ISOException.throwIt(S)V
		// 12
		staticMethodRef Api_1_Hdv_Gsr_1/checkException(Luicc/hci/framework/HCIException;)V;
			.descriptor	Luicc/hci/framework/HCIException;	1.3;

		// 13
		.classRef 3.2;		// uicc/hci/services/connectivity/ConnectivityService
		// 14
		virtualMethodRef 0.3.1()V;		// register()V
		// 15
		.classRef 4.2;		// uicc/hci/services/readermode/ReaderService
		// 16
		.classRef Api_1_Hdv_Gsr_1;
		// 17
		virtualMethodRef 0.13.1()S;		// getReason()S
		// 18
		virtualMethodRef 1.3.1()S;		// getReason()S
		// 19
		staticMethodRef Api_1_Hdv_Gsr_1/<init>()V;
		// 20
		virtualMethodRef 0.3.1()V;		// register()V
		// 21
		.classRef Api_1_Hdv_Gsr_2;
		// 22
		staticMethodRef Api_1_Hdv_Gsr_2/<init>()V;
		// 23
		virtualMethodRef 0.3.3()Z;		// selectingApplet()Z
		// 24
		virtualMethodRef 0.10.6()S;		// setIncomingAndReceive()S
	}

	.class public Api_1_Hdv_Gsr_1 0 extends 0.3 {		// extends javacard/framework/Applet

		.shareable;

		.fields {
			private 2.2 ceService 0;		// Luicc/hci/services/cardemulation/CardEmulationService;
			private 3.2 cnnService 1;		// Luicc/hci/services/connectivity/ConnectivityService;
			private 4.2 rmService 2;		// Luicc/hci/services/readermode/ReaderService;
			private static final short SW_SERVICE_NOT_SUPPORTED = 28417;		// S
			private static final short SW_SERVICE_NOT_SUPPORTED_AS_EXPECTED = -28671;		// S
			private static final short SW_SERVICE_ACCESS_NOT_GRANTED = -28670;		// S
			private static final short INS_HCI_CE_SERVCE = 1;		// S
			private static final short INS_HCI_CNN_SERVCE = 2;		// S
			private static final short INS_HCI_RM_SERVCE = 3;		// S
			private static final short INS_HCI_ILLEGAL_SERVCE = 4;		// S
		}

		.publicMethodTable 7 {
			equals(Ljava/lang/Object;)Z;
			register()V;
			register([BSB)V;
			selectingApplet()Z;
			deselect()V;
			getShareableInterfaceObject(Ljavacard/framework/AID;B)Ljavacard/framework/Shareable;;
			select()Z;
			process(Ljavacard/framework/APDU;)V;
			onCallback(BLuicc/hci/framework/HCIMessage;)V;
		}

		.packageMethodTable 0 {
		}

		.implementedInterfaceInfoTable { 
			.interface 0.2 { 		// javacard/framework/Shareable
			}

			.interface 1.0 { 		// uicc/hci/framework/HCIListener
				8;		// onCallback(BLuicc/hci/framework/HCIMessage;)V
			}

			.interface 2.0 { 		// uicc/hci/services/cardemulation/CardEmulationListener
				8;		// onCallback(BLuicc/hci/framework/HCIMessage;)V
			}

		}

		.method private <init>()V {
			.stack 1;
			.locals 0;

				L0:	aload_0;
					invokespecial 10;		// javacard/framework/Applet.<init>()V
					aload_0;
					invokevirtual 14;		// register()V
					return;
		}

		.method public static install([BSB)V 0 {
			.stack 2;
			.locals 0;

				L0:	new 16;		// uicc/hci/test/framework/api_1_hdv_gsr/Api_1_Hdv_Gsr_1
					dup;
					invokespecial 19;		// uicc/hci/test/framework/api_1_hdv_gsr/Api_1_Hdv_Gsr_1.<init>()V
					pop;
					return;
		}

		.method public process(Ljavacard/framework/APDU;)V 7 {
			.stack 2;
			.locals 3;

			.descriptor	Ljavacard/framework/APDU;	0.10;

				L0:	aload_0;
					invokevirtual 6;		// selectingApplet()Z
					ifeq L2;
				L1:	return;
				L2:	aload_1;
					invokevirtual 7;		// getBuffer()[B
					astore_2;
					aload_2;
					sconst_1;
					baload;
					stableswitch L24 1 4 L3 L8 L13 L18;
				L3:	aload_0;
					sconst_3;
					invokestatic 8;		// uicc/hci/framework/HCIDevice.getHCIService(S)Luicc/hci/framework/HCIService;
					checkcast 0 9;		// T_CLASSORINTERFACE uicc/hci/services/cardemulation/CardEmulationService
					putfield_a 0;		// reference uicc/hci/test/framework/api_1_hdv_gsr/Api_1_Hdv_Gsr_1.ceService
					getfield_a_this 0;		// reference uicc/hci/test/framework/api_1_hdv_gsr/Api_1_Hdv_Gsr_1.ceService
					ifnonnull L5;
				L4:	sspush 27264;
					invokestatic 11;		// javacard/framework/ISOException.throwIt(S)V
				L5:	goto L7;
				L6:	astore_3;
					aload_0;
					aload_3;
					invokespecial 12;		// uicc/hci/test/framework/api_1_hdv_gsr/Api_1_Hdv_Gsr_1.checkException(Luicc/hci/framework/HCIException;)V
				L7:	return;
				L8:	aload_0;
					sconst_4;
					invokestatic 8;		// uicc/hci/framework/HCIDevice.getHCIService(S)Luicc/hci/framework/HCIService;
					checkcast 0 13;		// T_CLASSORINTERFACE uicc/hci/services/connectivity/ConnectivityService
					putfield_a 1;		// reference uicc/hci/test/framework/api_1_hdv_gsr/Api_1_Hdv_Gsr_1.cnnService
					getfield_a_this 1;		// reference uicc/hci/test/framework/api_1_hdv_gsr/Api_1_Hdv_Gsr_1.cnnService
					ifnonnull L10;
				L9:	sspush 27264;
					invokestatic 11;		// javacard/framework/ISOException.throwIt(S)V
				L10:	goto L12;
				L11:	astore_3;
					aload_0;
					aload_3;
					invokespecial 12;		// uicc/hci/test/framework/api_1_hdv_gsr/Api_1_Hdv_Gsr_1.checkException(Luicc/hci/framework/HCIException;)V
				L12:	return;
				L13:	aload_0;
					sconst_2;
					invokestatic 8;		// uicc/hci/framework/HCIDevice.getHCIService(S)Luicc/hci/framework/HCIService;
					checkcast 0 15;		// T_CLASSORINTERFACE uicc/hci/services/readermode/ReaderService
					putfield_a 2;		// reference uicc/hci/test/framework/api_1_hdv_gsr/Api_1_Hdv_Gsr_1.rmService
					getfield_a_this 2;		// reference uicc/hci/test/framework/api_1_hdv_gsr/Api_1_Hdv_Gsr_1.rmService
					ifnonnull L15;
				L14:	sspush 27264;
					invokestatic 11;		// javacard/framework/ISOException.throwIt(S)V
				L15:	goto L17;
				L16:	astore_3;
					aload_0;
					aload_3;
					invokespecial 12;		// uicc/hci/test/framework/api_1_hdv_gsr/Api_1_Hdv_Gsr_1.checkException(Luicc/hci/framework/HCIException;)V
				L17:	return;
				L18:	sconst_m1;
					sstore_3;
				L19:	sload_3;
					invokestatic 8;		// uicc/hci/framework/HCIDevice.getHCIService(S)Luicc/hci/framework/HCIService;
					pop;
				L20:	goto L23;
				L21:	astore 4;
					aload 4;
					invokevirtual 17;		// getReason()S
					sconst_1;
					if_scmpne L23;
				L22:	return;
				L23:	sspush 28417;
					invokestatic 11;		// javacard/framework/ISOException.throwIt(S)V
				L24:	sspush 27264;
					invokestatic 11;		// javacard/framework/ISOException.throwIt(S)V
					return;
			.exceptionTable {
				// start_block end_block handler_block catch_type_index
				L3 L5 L6 4;
				L8 L10 L11 4;
				L13 L15 L16 4;
				L19 L20 L21 5;
			}
		}

		.method private checkException(Luicc/hci/framework/HCIException;)V {
			.stack 2;
			.locals 0;

			.descriptor	Luicc/hci/framework/HCIException;	1.3;

				L0:	aload_1;
					invokevirtual 18;		// getReason()S
					sconst_2;
					if_scmpne L2;
				L1:	sspush -28671;
					invokestatic 11;		// javacard/framework/ISOException.throwIt(S)V
				L2:	aload_1;
					invokevirtual 18;		// getReason()S
					sconst_1;
					if_scmpne L4;
				L3:	sspush -28670;
					invokestatic 11;		// javacard/framework/ISOException.throwIt(S)V
				L4:	sspush 28417;
					invokestatic 11;		// javacard/framework/ISOException.throwIt(S)V
					return;
		}

		.method public onCallback(BLuicc/hci/framework/HCIMessage;)V 8 {
			.stack 0;
			.locals 0;

			.descriptor	Luicc/hci/framework/HCIMessage;	1.1;

				L0:	return;
		}

	}

	.class public Api_1_Hdv_Gsr_2 1 extends 0.3 {		// extends javacard/framework/Applet

		.shareable;

		.fields {
			private boolean isNoServiceBeforeRegister 0;		// Z
			private static final short SW_SERVICE_NOT_SUPPORTED = 28417;		// S
			private static final byte INS_HCI_NO_SERVCE = 1;		// B
		}

		.publicMethodTable 7 {
			equals(Ljava/lang/Object;)Z;
			register()V;
			register([BSB)V;
			selectingApplet()Z;
			deselect()V;
			getShareableInterfaceObject(Ljavacard/framework/AID;B)Ljavacard/framework/Shareable;;
			select()Z;
			process(Ljavacard/framework/APDU;)V;
			onCallback(BLuicc/hci/framework/HCIMessage;)V;
		}

		.packageMethodTable 0 {
		}

		.implementedInterfaceInfoTable { 
			.interface 0.2 { 		// javacard/framework/Shareable
			}

			.interface 1.0 { 		// uicc/hci/framework/HCIListener
				8;		// onCallback(BLuicc/hci/framework/HCIMessage;)V
			}

			.interface 2.0 { 		// uicc/hci/services/cardemulation/CardEmulationListener
				8;		// onCallback(BLuicc/hci/framework/HCIMessage;)V
			}

		}

		.method private <init>()V {
			.stack 2;
			.locals 1;

				L0:	aload_0;
					invokespecial 10;		// javacard/framework/Applet.<init>()V
					aload_0;
					sconst_0;
					putfield_b 3;		// boolean uicc/hci/test/framework/api_1_hdv_gsr/Api_1_Hdv_Gsr_2.isNoServiceBeforeRegister
				L1:	sconst_3;
					invokestatic 8;		// uicc/hci/framework/HCIDevice.getHCIService(S)Luicc/hci/framework/HCIService;
					ifnonnull L3;
				L2:	aload_0;
					sconst_1;
					putfield_b 3;		// boolean uicc/hci/test/framework/api_1_hdv_gsr/Api_1_Hdv_Gsr_2.isNoServiceBeforeRegister
				L3:	goto L5;
				L4:	astore_1;
					sspush 28417;
					invokestatic 11;		// javacard/framework/ISOException.throwIt(S)V
				L5:	aload_0;
					invokevirtual 20;		// register()V
					return;
			.exceptionTable {
				// start_block end_block handler_block catch_type_index
				L1 L3 L4 4;
			}
		}

		.method public static install([BSB)V 0 {
			.stack 2;
			.locals 0;

				L0:	new 21;		// uicc/hci/test/framework/api_1_hdv_gsr/Api_1_Hdv_Gsr_2
					dup;
					invokespecial 22;		// uicc/hci/test/framework/api_1_hdv_gsr/Api_1_Hdv_Gsr_2.<init>()V
					pop;
					return;
		}

		.method public process(Ljavacard/framework/APDU;)V 7 {
			.stack 2;
			.locals 1;

			.descriptor	Ljavacard/framework/APDU;	0.10;

				L0:	aload_0;
					invokevirtual 23;		// selectingApplet()Z
					ifeq L2;
				L1:	return;
				L2:	aload_1;
					invokevirtual 7;		// getBuffer()[B
					astore_2;
					aload_1;
					invokevirtual 24;		// setIncomingAndReceive()S
					pop;
					aload_2;
					sconst_1;
					baload;
					slookupswitch L6 1 1 L3;
				L3:	getfield_b_this 3;		// boolean uicc/hci/test/framework/api_1_hdv_gsr/Api_1_Hdv_Gsr_2.isNoServiceBeforeRegister
					ifeq L5;
				L4:	return;
				L5:	sspush 28417;
					invokestatic 11;		// javacard/framework/ISOException.throwIt(S)V
				L6:	sspush 27904;
					invokestatic 11;		// javacard/framework/ISOException.throwIt(S)V
					return;
		}

		.method public onCallback(BLuicc/hci/framework/HCIMessage;)V 8 {
			.stack 0;
			.locals 0;

			.descriptor	Luicc/hci/framework/HCIMessage;	1.1;

				L0:	return;
		}

	}

}
